Workbook

Sheet Executive Summary
A1: Executive Summary
A3: ="Polish Housing Market — 17 major cities | Prices: "&src_city_snapshot!$AS$2&" • Affordability & full-year supply: "&src_city_snapshot!$AT$2&" • Current supply update: H1 "&src_city_snapshot!$AW$2&" vs H1 "&(src_city_snapshot!$AW$2-1) -> Polish Housing Market — 17 major cities | Prices: 2026Q2 • Affordability & full-year supply: 2025 • Current supply update: H1 2026 vs H1 2025
A4: Median Secondary Price | D4: Median Primary Price | G4: Median Affordability | J4: Median Completed Supply
A5: =MEDIAN('City Comparison'!B8:B24) -> 9403.1318 | D5: =MEDIAN('City Comparison'!C8:C24) -> 11427.47 | G5: =MEDIAN('City Comparison'!E8:E24) -> 0.95897791 | J5: =MEDIAN('City Comparison'!G8:G24) -> 8.3991882
A8: ="Reference: "&src_city_snapshot!$AS$2 -> Reference: 2026Q2 | D8: ="Reference: "&src_city_snapshot!$AS$2 -> Reference: 2026Q2 | G8: ="Reference: "&src_city_snapshot!$AT$2 -> Reference: 2025 | J8: ="Reference: "&src_city_snapshot!$AV$2 -> Reference: 2025
A10: ="Housing completions — H1 "&src_city_snapshot!$AW$2&" vs H1 "&(src_city_snapshot!$AW$2-1) -> Housing completions — H1 2026 vs H1 2025
A29: ="Key takeaways — H1 "&src_city_snapshot!$AW$2&" supply update" -> Key takeaways — H1 2026 supply update
A30: ="Median change across 17 cities: "&TEXT(MEDIAN('City Comparison'!$J$8:$J$24),"0.0%")&"." -> Median change across 17 cities: -8,6%.
A31: {="Largest increase in units: "&INDEX('City Comparison'!$A$8:$A$24,MATCH(MAX('City Comparison'!$K$8:$K$24),'City Comparison'!$K$8:$K$24,0))&": "&TEXT(MAX('City Comparison'!$K$8:$K$24),"+#,##0;-#,##0;0")&" dwellings ("&TEXT(INDEX('City Comparison'!$J$8:$J$24,MATCH(MAX('City Comparison'!$K$8:$K$24),'City Comparison'!$K$8:$K$24,0)),"0.0%")&")."} -> Largest increase in units: Kraków: +1 770 dwellings (64,8%).
A32: {="Largest decline in units: "&INDEX('City Comparison'!$A$8:$A$24,MATCH(MIN('City Comparison'!$K$8:$K$24),'City Comparison'!$K$8:$K$24,0))&": "&TEXT(MIN('City Comparison'!$K$8:$K$24),"+#,##0;-#,##0;0")&" dwellings ("&TEXT(INDEX('City Comparison'!$J$8:$J$24,MATCH(MIN('City Comparison'!$K$8:$K$24),'City Comparison'!$K$8:$K$24,0)),"0.0%")&")."} -> Largest decline in units: Warszawa: -1 433 dwellings (-17,3%).
A33: {="Largest percentage increase: "&INDEX('City Comparison'!$A$8:$A$24,MATCH(MAX('City Comparison'!$J$8:$J$24),'City Comparison'!$J$8:$J$24,0))&": "&TEXT(MAX('City Comparison'!$J$8:$J$24),"0.0%")&" ("&TEXT(INDEX('City Comparison'!$H$8:$H$24,MATCH(MAX('City Comparison'!$J$8:$J$24),'City Comparison'!$J$8:$J$24,0)),"#,##0")&" → "&TEXT(INDEX('City Comparison'!$I$8:$I$24,MATCH(MAX('City Comparison'!$J$8:$J$24),'City Comparison'!$J$8:$J$24,0)),"#,##0")&")."} -> Largest percentage increase: Olsztyn: 299,0% (195 → 778).
A35: ="Interpretation note: H1 "&src_city_snapshot!$AW$2&" is a partial-year period and is compared only with H1 "&(src_city_snapshot!$AW$2-1)&". KPI cards intentionally use different reference periods; see Methodology." -> Interpretation note: H1 2026 is a partial-year period and is compared only with H1 2025. KPI cards intentionally use different reference periods; see Methodology.
A37: Source: NBP BaRN, GUS BDL | Reporting tables prepared in Python | Definitions and periods: Methodology

Sheet City Comparison
A1: City Comparison
A3: 17 cities compared on individual metrics. No composite score.
A4: Use the header filters to sort or narrow the table. Red shading = relatively less buyer-favorable within that metric white = relatively more favorable. No overall city score.
A7: City | B7: Secondary Price PLN/m² | C7: Primary Price PLN/m² | D7: Primary Premium % | E7: Affordability m² / salary | F7: Price Growth latest 4 YoY avg % | G7: Supply 2025 completed / 1k | H7: H1 2025 completed | I7: H1 2026 completed | J7: H1 Supply Change % | K7: H1 Change units
A8: {=INDEX(src_dim_city!$B$2:$B$18,MATCH(helper_report!$A16,src_dim_city!$A$2:$A$18,0))} -> Warszawa | B8: {=INDEX(src_city_snapshot!$D$2:$D$18,MATCH(helper_report!$A16,src_city_snapshot!$A$2:$A$18,0))} -> 16722.657 | C8: {=INDEX(src_city_snapshot!$C$2:$C$18,MATCH(helper_report!$A16,src_city_snapshot!$A$2:$A$18,0))} -> 16783.491 | D8: {=INDEX(src_city_snapshot!$K$2:$K$18,MATCH(helper_report!$A16,src_city_snapshot!$A$2:$A$18,0))} -> 0.36378587 | E8: {=INDEX(src_city_snapshot!$U$2:$U$18,MATCH(helper_report!$A16,src_city_snapshot!$A$2:$A$18,0))} -> 0.70416855 | F8: {=INDEX(src_city_snapshot!$I$2:$I$18,MATCH(helper_report!$A16,src_city_snapshot!$A$2:$A$18,0))} -> -0.82738646 | G8: {=INDEX(src_city_snapshot!$AK$2:$AK$18,MATCH(helper_report!$A16,src_city_snapshot!$A$2:$A$18,0))} -> 10.645723 | H8: =SUMIFS(src_fact_city_year!$AI$2:$AI$375,src_fact_city_year!$A$2:$A$375,helper_report!$A16,src_fact_city_year!$B$2:$B$375,src_city_snapshot!$AW$2-1) -> 8300 | I8: =SUMIFS(src_fact_city_year!$AI$2:$AI$375,src_fact_city_year!$A$2:$A$375,helper_report!$A16,src_fact_city_year!$B$2:$B$375,src_city_snapshot!$AW$2) -> 6867 | J8: =IFERROR(I8/H8-1,"") -> -0.1726506 | K8: =IF(OR(H8="",I8=""),"",I8-H8) -> -1433
A9: {=INDEX(src_dim_city!$B$2:$B$18,MATCH(helper_report!$A8,src_dim_city!$A$2:$A$18,0))} -> Kraków | B9: {=INDEX(src_city_snapshot!$D$2:$D$18,MATCH(helper_report!$A8,src_city_snapshot!$A$2:$A$18,0))} -> 14791.951 | C9: {=INDEX(src_city_snapshot!$C$2:$C$18,MATCH(helper_report!$A8,src_city_snapshot!$A$2:$A$18,0))} -> 15922.877 | D9: {=INDEX(src_city_snapshot!$K$2:$K$18,MATCH(helper_report!$A8,src_city_snapshot!$A$2:$A$18,0))} -> 7.6455528 | E9: {=INDEX(src_city_snapshot!$U$2:$U$18,MATCH(helper_report!$A8,src_city_snapshot!$A$2:$A$18,0))} -> 0.76133116 | F9: {=INDEX(src_city_snapshot!$I$2:$I$18,MATCH(helper_report!$A8,src_city_snapshot!$A$2:$A$18,0))} -> -1.084829 | G9: {=INDEX(src_city_snapshot!$AK$2:$AK$18,MATCH(helper_report!$A8,src_city_snapshot!$A$2:$A$18,0))} -> 9.8027363 | H9: =SUMIFS(src_fact_city_year!$AI$2:$AI$375,src_fact_city_year!$A$2:$A$375,helper_report!$A8,src_fact_city_year!$B$2:$B$375,src_city_snapshot!$AW$2-1) -> 2731 | I9: =SUMIFS(src_fact_city_year!$AI$2:$AI$375,src_fact_city_year!$A$2:$A$375,helper_report!$A8,src_fact_city_year!$B$2:$B$375,src_city_snapshot!$AW$2) -> 4501 | J9: =IFERROR(I9/H9-1,"") -> 0.64811424 | K9: =IF(OR(H9="",I9=""),"",I9-H9) -> 1770
A10: {=INDEX(src_dim_city!$B$2:$B$18,MATCH(helper_report!$A4,src_dim_city!$A$2:$A$18,0))} -> Gdańsk | B10: {=INDEX(src_city_snapshot!$D$2:$D$18,MATCH(helper_report!$A4,src_city_snapshot!$A$2:$A$18,0))} -> 14034.642 | C10: {=INDEX(src_city_snapshot!$C$2:$C$18,MATCH(helper_report!$A4,src_city_snapshot!$A$2:$A$18,0))} -> 14490.615 | D10: {=INDEX(src_city_snapshot!$K$2:$K$18,MATCH(helper_report!$A4,src_city_snapshot!$A$2:$A$18,0))} -> 3.248908 | E10: {=INDEX(src_city_snapshot!$U$2:$U$18,MATCH(helper_report!$A4,src_city_snapshot!$A$2:$A$18,0))} -> 0.82103419 | F10: {=INDEX(src_city_snapshot!$I$2:$I$18,MATCH(helper_report!$A4,src_city_snapshot!$A$2:$A$18,0))} -> 4.4716399 | G10: {=INDEX(src_city_snapshot!$AK$2:$AK$18,MATCH(helper_report!$A4,src_city_snapshot!$A$2:$A$18,0))} -> 11.754845 | H10: =SUMIFS(src_fact_city_year!$AI$2:$AI$375,src_fact_city_year!$A$2:$A$375,helper_report!$A4,src_fact_city_year!$B$2:$B$375,src_city_snapshot!$AW$2-1) -> 2194 | I10: =SUMIFS(src_fact_city_year!$AI$2:$AI$375,src_fact_city_year!$A$2:$A$375,helper_report!$A4,src_fact_city_year!$B$2:$B$375,src_city_snapshot!$AW$2) -> 1618 | J10: =IFERROR(I10/H10-1,"") -> -0.26253418 | K10: =IF(OR(H10="",I10=""),"",I10-H10) -> -576
A11: {=INDEX(src_dim_city!$B$2:$B$18,MATCH(helper_report!$A17,src_dim_city!$A$2:$A$18,0))} -> Wrocław | B11: {=INDEX(src_city_snapshot!$D$2:$D$18,MATCH(helper_report!$A17,src_city_snapshot!$A$2:$A$18,0))} -> 12589.783 | C11: {=INDEX(src_city_snapshot!$C$2:$C$18,MATCH(helper_report!$A17,src_city_snapshot!$A$2:$A$18,0))} -> 14312.254 | D11: {=INDEX(src_city_snapshot!$K$2:$K$18,MATCH(helper_report!$A17,src_city_snapshot!$A$2:$A$18,0))} -> 13.681501 | E11: {=INDEX(src_city_snapshot!$U$2:$U$18,MATCH(helper_report!$A17,src_city_snapshot!$A$2:$A$18,0))} -> 0.80601293 | F11: {=INDEX(src_city_snapshot!$I$2:$I$18,MATCH(helper_report!$A17,src_city_snapshot!$A$2:$A$18,0))} -> -1.3611285 | G11: {=INDEX(src_city_snapshot!$AK$2:$AK$18,MATCH(helper_report!$A17,src_city_snapshot!$A$2:$A$18,0))} -> 11.449048 | H11: =SUMIFS(src_fact_city_year!$AI$2:$AI$375,src_fact_city_year!$A$2:$A$375,helper_report!$A17,src_fact_city_year!$B$2:$B$375,src_city_snapshot!$AW$2-1) -> 3481 | I11: =SUMIFS(src_fact_city_year!$AI$2:$AI$375,src_fact_city_year!$A$2:$A$375,helper_report!$A17,src_fact_city_year!$B$2:$B$375,src_city_snapshot!$AW$2) -> 3182 | J11: =IFERROR(I11/H11-1,"") -> -0.085894858 | K11: =IF(OR(H11="",I11=""),"",I11-H11) -> -299
A12: {=INDEX(src_dim_city!$B$2:$B$18,MATCH(helper_report!$A5,src_dim_city!$A$2:$A$18,0))} -> Gdynia | B12: {=INDEX(src_city_snapshot!$D$2:$D$18,MATCH(helper_report!$A5,src_city_snapshot!$A$2:$A$18,0))} -> 12266.795 | C12: {=INDEX(src_city_snapshot!$C$2:$C$18,MATCH(helper_report!$A5,src_city_snapshot!$A$2:$A$18,0))} -> 12886.982 | D12: {=INDEX(src_city_snapshot!$K$2:$K$18,MATCH(helper_report!$A5,src_city_snapshot!$A$2:$A$18,0))} -> 5.0558178 | E12: {=INDEX(src_city_snapshot!$U$2:$U$18,MATCH(helper_report!$A5,src_city_snapshot!$A$2:$A$18,0))} -> 0.83120516 | F12: {=INDEX(src_city_snapshot!$I$2:$I$18,MATCH(helper_report!$A5,src_city_snapshot!$A$2:$A$18,0))} -> 1.4936952 | G12: {=INDEX(src_city_snapshot!$AK$2:$AK$18,MATCH(helper_report!$A5,src_city_snapshot!$A$2:$A$18,0))} -> 3.6101536 | H12: =SUMIFS(src_fact_city_year!$AI$2:$AI$375,src_fact_city_year!$A$2:$A$375,helper_report!$A5,src_fact_city_year!$B$2:$B$375,src_city_snapshot!$AW$2-1) -> 296 | I12: =SUMIFS(src_fact_city_year!$AI$2:$AI$375,src_fact_city_year!$A$2:$A$375,helper_report!$A5,src_fact_city_year!$B$2:$B$375,src_city_snapshot!$AW$2) -> 247 | J12: =IFERROR(I12/H12-1,"") -> -0.16554054 | K12: =IF(OR(H12="",I12=""),"",I12-H12) -> -49
A13: {=INDEX(src_dim_city!$B$2:$B$18,MATCH(helper_report!$A14,src_dim_city!$A$2:$A$18,0))} -> Rzeszów | B13: {=INDEX(src_city_snapshot!$D$2:$D$18,MATCH(helper_report!$A14,src_city_snapshot!$A$2:$A$18,0))} -> 10973.994 | C13: {=INDEX(src_city_snapshot!$C$2:$C$18,MATCH(helper_report!$A14,src_city_snapshot!$A$2:$A$18,0))} -> 10329.021 | D13: {=INDEX(src_city_snapshot!$K$2:$K$18,MATCH(helper_report!$A14,src_city_snapshot!$A$2:$A$18,0))} -> -5.8772826 | E13: {=INDEX(src_city_snapshot!$U$2:$U$18,MATCH(helper_report!$A14,src_city_snapshot!$A$2:$A$18,0))} -> 0.89436017 | F13: {=INDEX(src_city_snapshot!$I$2:$I$18,MATCH(helper_report!$A14,src_city_snapshot!$A$2:$A$18,0))} -> 1.9723635 | G13: {=INDEX(src_city_snapshot!$AK$2:$AK$18,MATCH(helper_report!$A14,src_city_snapshot!$A$2:$A$18,0))} -> 15.598872 | H13: =SUMIFS(src_fact_city_year!$AI$2:$AI$375,src_fact_city_year!$A$2:$A$375,helper_report!$A14,src_fact_city_year!$B$2:$B$375,src_city_snapshot!$AW$2-1) -> 1714 | I13: =SUMIFS(src_fact_city_year!$AI$2:$AI$375,src_fact_city_year!$A$2:$A$375,helper_report!$A14,src_fact_city_year!$B$2:$B$375,src_city_snapshot!$AW$2) -> 1526 | J13: =IFERROR(I13/H13-1,"") -> -0.10968495 | K13: =IF(OR(H13="",I13=""),"",I13-H13) -> -188
A14: {=INDEX(src_dim_city!$B$2:$B$18,MATCH(helper_report!$A13,src_dim_city!$A$2:$A$18,0))} -> Poznań | B14: {=INDEX(src_city_snapshot!$D$2:$D$18,MATCH(helper_report!$A13,src_city_snapshot!$A$2:$A$18,0))} -> 10890.792 | C14: {=INDEX(src_city_snapshot!$C$2:$C$18,MATCH(helper_report!$A13,src_city_snapshot!$A$2:$A$18,0))} -> 12765.859 | D14: {=INDEX(src_city_snapshot!$K$2:$K$18,MATCH(helper_report!$A13,src_city_snapshot!$A$2:$A$18,0))} -> 17.216996 | E14: {=INDEX(src_city_snapshot!$U$2:$U$18,MATCH(helper_report!$A13,src_city_snapshot!$A$2:$A$18,0))} -> 0.94172939 | F14: {=INDEX(src_city_snapshot!$I$2:$I$18,MATCH(helper_report!$A13,src_city_snapshot!$A$2:$A$18,0))} -> 1.6999744 | G14: {=INDEX(src_city_snapshot!$AK$2:$AK$18,MATCH(helper_report!$A13,src_city_snapshot!$A$2:$A$18,0))} -> 10.483948 | H14: =SUMIFS(src_fact_city_year!$AI$2:$AI$375,src_fact_city_year!$A$2:$A$375,helper_report!$A13,src_fact_city_year!$B$2:$B$375,src_city_snapshot!$AW$2-1) -> 1791 | I14: =SUMIFS(src_fact_city_year!$AI$2:$AI$375,src_fact_city_year!$A$2:$A$375,helper_report!$A13,src_fact_city_year!$B$2:$B$375,src_city_snapshot!$AW$2) -> 2319 | J14: =IFERROR(I14/H14-1,"") -> 0.29480737 | K14: =IF(OR(H14="",I14=""),"",I14-H14) -> 528
A15: {=INDEX(src_dim_city!$B$2:$B$18,MATCH(helper_report!$A9,src_dim_city!$A$2:$A$18,0))} -> Lublin | B15: {=INDEX(src_city_snapshot!$D$2:$D$18,MATCH(helper_report!$A9,src_city_snapshot!$A$2:$A$18,0))} -> 10219.03 | C15: {=INDEX(src_city_snapshot!$C$2:$C$18,MATCH(helper_report!$A9,src_city_snapshot!$A$2:$A$18,0))} -> 10889.14 | D15: {=INDEX(src_city_snapshot!$K$2:$K$18,MATCH(helper_report!$A9,src_city_snapshot!$A$2:$A$18,0))} -> 6.5574717 | E15: {=INDEX(src_city_snapshot!$U$2:$U$18,MATCH(helper_report!$A9,src_city_snapshot!$A$2:$A$18,0))} -> 0.92680109 | F15: {=INDEX(src_city_snapshot!$I$2:$I$18,MATCH(helper_report!$A9,src_city_snapshot!$A$2:$A$18,0))} -> 1.9584294 | G15: {=INDEX(src_city_snapshot!$AK$2:$AK$18,MATCH(helper_report!$A9,src_city_snapshot!$A$2:$A$18,0))} -> 8.879481 | H15: =SUMIFS(src_fact_city_year!$AI$2:$AI$375,src_fact_city_year!$A$2:$A$375,helper_report!$A9,src_fact_city_year!$B$2:$B$375,src_city_snapshot!$AW$2-1) -> 934 | I15: =SUMIFS(src_fact_city_year!$AI$2:$AI$375,src_fact_city_year!$A$2:$A$375,helper_report!$A9,src_fact_city_year!$B$2:$B$375,src_city_snapshot!$AW$2) -> 1433 | J15: =IFERROR(I15/H15-1,"") -> 0.53426124 | K15: =IF(OR(H15="",I15=""),"",I15-H15) -> 499
A16: {=INDEX(src_dim_city!$B$2:$B$18,MATCH(helper_report!$A2,src_dim_city!$A$2:$A$18,0))} -> Białystok | B16: {=INDEX(src_city_snapshot!$D$2:$D$18,MATCH(helper_report!$A2,src_city_snapshot!$A$2:$A$18,0))} -> 9403.1318 | C16: {=INDEX(src_city_snapshot!$C$2:$C$18,MATCH(helper_report!$A2,src_city_snapshot!$A$2:$A$18,0))} -> 10926.219 | D16: {=INDEX(src_city_snapshot!$K$2:$K$18,MATCH(helper_report!$A2,src_city_snapshot!$A$2:$A$18,0))} -> 16.197656 | E16: {=INDEX(src_city_snapshot!$U$2:$U$18,MATCH(helper_report!$A2,src_city_snapshot!$A$2:$A$18,0))} -> 0.95897791 | F16: {=INDEX(src_city_snapshot!$I$2:$I$18,MATCH(helper_report!$A2,src_city_snapshot!$A$2:$A$18,0))} -> 0.65780585 | G16: {=INDEX(src_city_snapshot!$AK$2:$AK$18,MATCH(helper_report!$A2,src_city_snapshot!$A$2:$A$18,0))} -> 5.8442791 | H16: =SUMIFS(src_fact_city_year!$AI$2:$AI$375,src_fact_city_year!$A$2:$A$375,helper_report!$A2,src_fact_city_year!$B$2:$B$375,src_city_snapshot!$AW$2-1) -> 1120 | I16: =SUMIFS(src_fact_city_year!$AI$2:$AI$375,src_fact_city_year!$A$2:$A$375,helper_report!$A2,src_fact_city_year!$B$2:$B$375,src_city_snapshot!$AW$2) -> 311 | J16: =IFERROR(I16/H16-1,"") -> -0.72232143 | K16: =IF(OR(H16="",I16=""),"",I16-H16) -> -809
A17: {=INDEX(src_dim_city!$B$2:$B$18,MATCH(helper_report!$A15,src_dim_city!$A$2:$A$18,0))} -> Szczecin | B17: {=INDEX(src_city_snapshot!$D$2:$D$18,MATCH(helper_report!$A15,src_city_snapshot!$A$2:$A$18,0))} -> 9363.2163 | C17: {=INDEX(src_city_snapshot!$C$2:$C$18,MATCH(helper_report!$A15,src_city_snapshot!$A$2:$A$18,0))} -> 11427.47 | D17: {=INDEX(src_city_snapshot!$K$2:$K$18,MATCH(helper_report!$A15,src_city_snapshot!$A$2:$A$18,0))} -> 22.046419 | E17: {=INDEX(src_city_snapshot!$U$2:$U$18,MATCH(helper_report!$A15,src_city_snapshot!$A$2:$A$18,0))} -> 1.069479 | F17: {=INDEX(src_city_snapshot!$I$2:$I$18,MATCH(helper_report!$A15,src_city_snapshot!$A$2:$A$18,0))} -> 1.4283439 | G17: {=INDEX(src_city_snapshot!$AK$2:$AK$18,MATCH(helper_report!$A15,src_city_snapshot!$A$2:$A$18,0))} -> 6.1792823 | H17: =SUMIFS(src_fact_city_year!$AI$2:$AI$375,src_fact_city_year!$A$2:$A$375,helper_report!$A15,src_fact_city_year!$B$2:$B$375,src_city_snapshot!$AW$2-1) -> 961 | I17: =SUMIFS(src_fact_city_year!$AI$2:$AI$375,src_fact_city_year!$A$2:$A$375,helper_report!$A15,src_fact_city_year!$B$2:$B$375,src_city_snapshot!$AW$2) -> 680 | J17: =IFERROR(I17/H17-1,"") -> -0.29240375 | K17: =IF(OR(H17="",I17=""),"",I17-H17) -> -281
A18: {=INDEX(src_dim_city!$B$2:$B$18,MATCH(helper_report!$A12,src_dim_city!$A$2:$A$18,0))} -> Opole | B18: {=INDEX(src_city_snapshot!$D$2:$D$18,MATCH(helper_report!$A12,src_city_snapshot!$A$2:$A$18,0))} -> 9215.2766 | C18: {=INDEX(src_city_snapshot!$C$2:$C$18,MATCH(helper_report!$A12,src_city_snapshot!$A$2:$A$18,0))} -> 11624.601 | D18: {=INDEX(src_city_snapshot!$K$2:$K$18,MATCH(helper_report!$A12,src_city_snapshot!$A$2:$A$18,0))} -> 26.144899 | E18: {=INDEX(src_city_snapshot!$U$2:$U$18,MATCH(helper_report!$A12,src_city_snapshot!$A$2:$A$18,0))} -> 1.0657993 | F18: {=INDEX(src_city_snapshot!$I$2:$I$18,MATCH(helper_report!$A12,src_city_snapshot!$A$2:$A$18,0))} -> 3.8899978 | G18: {=INDEX(src_city_snapshot!$AK$2:$AK$18,MATCH(helper_report!$A12,src_city_snapshot!$A$2:$A$18,0))} -> 2.9177825 | H18: =SUMIFS(src_fact_city_year!$AI$2:$AI$375,src_fact_city_year!$A$2:$A$375,helper_report!$A12,src_fact_city_year!$B$2:$B$375,src_city_snapshot!$AW$2-1) -> 165 | I18: =SUMIFS(src_fact_city_year!$AI$2:$AI$375,src_fact_city_year!$A$2:$A$375,helper_report!$A12,src_fact_city_year!$B$2:$B$375,src_city_snapshot!$AW$2) -> 323 | J18: =IFERROR(I18/H18-1,"") -> 0.95757576 | K18: =IF(OR(H18="",I18=""),"",I18-H18) -> 158
A19: {=INDEX(src_dim_city!$B$2:$B$18,MATCH(helper_report!$A11,src_dim_city!$A$2:$A$18,0))} -> Olsztyn | B19: {=INDEX(src_city_snapshot!$D$2:$D$18,MATCH(helper_report!$A11,src_city_snapshot!$A$2:$A$18,0))} -> 8940.509 | C19: {=INDEX(src_city_snapshot!$C$2:$C$18,MATCH(helper_report!$A11,src_city_snapshot!$A$2:$A$18,0))} -> 10680.51 | D19: {=INDEX(src_city_snapshot!$K$2:$K$18,MATCH(helper_report!$A11,src_city_snapshot!$A$2:$A$18,0))} -> 19.46199 | E19: {=INDEX(src_city_snapshot!$U$2:$U$18,MATCH(helper_report!$A11,src_city_snapshot!$A$2:$A$18,0))} -> 1.0801307 | F19: {=INDEX(src_city_snapshot!$I$2:$I$18,MATCH(helper_report!$A11,src_city_snapshot!$A$2:$A$18,0))} -> 3.8693641 | G19: {=INDEX(src_city_snapshot!$AK$2:$AK$18,MATCH(helper_report!$A11,src_city_snapshot!$A$2:$A$18,0))} -> 3.6176178 | H19: =SUMIFS(src_fact_city_year!$AI$2:$AI$375,src_fact_city_year!$A$2:$A$375,helper_report!$A11,src_fact_city_year!$B$2:$B$375,src_city_snapshot!$AW$2-1) -> 195 | I19: =SUMIFS(src_fact_city_year!$AI$2:$AI$375,src_fact_city_year!$A$2:$A$375,helper_report!$A11,src_fact_city_year!$B$2:$B$375,src_city_snapshot!$AW$2) -> 778 | J19: =IFERROR(I19/H19-1,"") -> 2.9897436 | K19: =IF(OR(H19="",I19=""),"",I19-H19) -> 583
A20: {=INDEX(src_dim_city!$B$2:$B$18,MATCH(helper_report!$A18,src_dim_city!$A$2:$A$18,0))} -> Zielona Góra | B20: {=INDEX(src_city_snapshot!$D$2:$D$18,MATCH(helper_report!$A18,src_city_snapshot!$A$2:$A$18,0))} -> 8633.384 | C20: {=INDEX(src_city_snapshot!$C$2:$C$18,MATCH(helper_report!$A18,src_city_snapshot!$A$2:$A$18,0))} -> 9457.8511 | D20: {=INDEX(src_city_snapshot!$K$2:$K$18,MATCH(helper_report!$A18,src_city_snapshot!$A$2:$A$18,0))} -> 9.549755 | E20: {=INDEX(src_city_snapshot!$U$2:$U$18,MATCH(helper_report!$A18,src_city_snapshot!$A$2:$A$18,0))} -> 1.1143175 | F20: {=INDEX(src_city_snapshot!$I$2:$I$18,MATCH(helper_report!$A18,src_city_snapshot!$A$2:$A$18,0))} -> 7.7493366 | G20: {=INDEX(src_city_snapshot!$AK$2:$AK$18,MATCH(helper_report!$A18,src_city_snapshot!$A$2:$A$18,0))} -> 7.6607091 | H20: =SUMIFS(src_fact_city_year!$AI$2:$AI$375,src_fact_city_year!$A$2:$A$375,helper_report!$A18,src_fact_city_year!$B$2:$B$375,src_city_snapshot!$AW$2-1) -> 397 | I20: =SUMIFS(src_fact_city_year!$AI$2:$AI$375,src_fact_city_year!$A$2:$A$375,helper_report!$A18,src_fact_city_year!$B$2:$B$375,src_city_snapshot!$AW$2) -> 296 | J20: =IFERROR(I20/H20-1,"") -> -0.25440806 | K20: =IF(OR(H20="",I20=""),"",I20-H20) -> -101
A21: {=INDEX(src_dim_city!$B$2:$B$18,MATCH(helper_report!$A3,src_dim_city!$A$2:$A$18,0))} -> Bydgoszcz | B21: {=INDEX(src_city_snapshot!$D$2:$D$18,MATCH(helper_report!$A3,src_city_snapshot!$A$2:$A$18,0))} -> 8341.8674 | C21: {=INDEX(src_city_snapshot!$C$2:$C$18,MATCH(helper_report!$A3,src_city_snapshot!$A$2:$A$18,0))} -> 10774.886 | D21: {=INDEX(src_city_snapshot!$K$2:$K$18,MATCH(helper_report!$A3,src_city_snapshot!$A$2:$A$18,0))} -> 29.166357 | E21: {=INDEX(src_city_snapshot!$U$2:$U$18,MATCH(helper_report!$A3,src_city_snapshot!$A$2:$A$18,0))} -> 1.1845936 | F21: {=INDEX(src_city_snapshot!$I$2:$I$18,MATCH(helper_report!$A3,src_city_snapshot!$A$2:$A$18,0))} -> 1.864496 | G21: {=INDEX(src_city_snapshot!$AK$2:$AK$18,MATCH(helper_report!$A3,src_city_snapshot!$A$2:$A$18,0))} -> 3.653121 | H21: =SUMIFS(src_fact_city_year!$AI$2:$AI$375,src_fact_city_year!$A$2:$A$375,helper_report!$A3,src_fact_city_year!$B$2:$B$375,src_city_snapshot!$AW$2-1) -> 345 | I21: =SUMIFS(src_fact_city_year!$AI$2:$AI$375,src_fact_city_year!$A$2:$A$375,helper_report!$A3,src_fact_city_year!$B$2:$B$375,src_city_snapshot!$AW$2) -> 985 | J21: =IFERROR(I21/H21-1,"") -> 1.8550725 | K21: =IF(OR(H21="",I21=""),"",I21-H21) -> 640
A22: {=INDEX(src_dim_city!$B$2:$B$18,MATCH(helper_report!$A7,src_dim_city!$A$2:$A$18,0))} -> Kielce | B22: {=INDEX(src_city_snapshot!$D$2:$D$18,MATCH(helper_report!$A7,src_city_snapshot!$A$2:$A$18,0))} -> 8192.6461 | C22: {=INDEX(src_city_snapshot!$C$2:$C$18,MATCH(helper_report!$A7,src_city_snapshot!$A$2:$A$18,0))} -> 10401.899 | D22: {=INDEX(src_city_snapshot!$K$2:$K$18,MATCH(helper_report!$A7,src_city_snapshot!$A$2:$A$18,0))} -> 26.966291 | E22: {=INDEX(src_city_snapshot!$U$2:$U$18,MATCH(helper_report!$A7,src_city_snapshot!$A$2:$A$18,0))} -> 1.1105757 | F22: {=INDEX(src_city_snapshot!$I$2:$I$18,MATCH(helper_report!$A7,src_city_snapshot!$A$2:$A$18,0))} -> 1.4904394 | G22: {=INDEX(src_city_snapshot!$AK$2:$AK$18,MATCH(helper_report!$A7,src_city_snapshot!$A$2:$A$18,0))} -> 5.8154418 | H22: =SUMIFS(src_fact_city_year!$AI$2:$AI$375,src_fact_city_year!$A$2:$A$375,helper_report!$A7,src_fact_city_year!$B$2:$B$375,src_city_snapshot!$AW$2-1) -> 587 | I22: =SUMIFS(src_fact_city_year!$AI$2:$AI$375,src_fact_city_year!$A$2:$A$375,helper_report!$A7,src_fact_city_year!$B$2:$B$375,src_city_snapshot!$AW$2) -> 493 | J22: =IFERROR(I22/H22-1,"") -> -0.16013629 | K22: =IF(OR(H22="",I22=""),"",I22-H22) -> -94
A23: {=INDEX(src_dim_city!$B$2:$B$18,MATCH(helper_report!$A6,src_dim_city!$A$2:$A$18,0))} -> Katowice | B23: {=INDEX(src_city_snapshot!$D$2:$D$18,MATCH(helper_report!$A6,src_city_snapshot!$A$2:$A$18,0))} -> 8101.6961 | C23: {=INDEX(src_city_snapshot!$C$2:$C$18,MATCH(helper_report!$A6,src_city_snapshot!$A$2:$A$18,0))} -> 11840.15 | D23: {=INDEX(src_city_snapshot!$K$2:$K$18,MATCH(helper_report!$A6,src_city_snapshot!$A$2:$A$18,0))} -> 46.144085 | E23: {=INDEX(src_city_snapshot!$U$2:$U$18,MATCH(helper_report!$A6,src_city_snapshot!$A$2:$A$18,0))} -> 1.3236617 | F23: {=INDEX(src_city_snapshot!$I$2:$I$18,MATCH(helper_report!$A6,src_city_snapshot!$A$2:$A$18,0))} -> 1.4105917 | G23: {=INDEX(src_city_snapshot!$AK$2:$AK$18,MATCH(helper_report!$A6,src_city_snapshot!$A$2:$A$18,0))} -> 8.3991882 | H23: =SUMIFS(src_fact_city_year!$AI$2:$AI$375,src_fact_city_year!$A$2:$A$375,helper_report!$A6,src_fact_city_year!$B$2:$B$375,src_city_snapshot!$AW$2-1) -> 1269 | I23: =SUMIFS(src_fact_city_year!$AI$2:$AI$375,src_fact_city_year!$A$2:$A$375,helper_report!$A6,src_fact_city_year!$B$2:$B$375,src_city_snapshot!$AW$2) -> 1420 | J23: =IFERROR(I23/H23-1,"") -> 0.11899133 | K23: =IF(OR(H23="",I23=""),"",I23-H23) -> 151
A24: {=INDEX(src_dim_city!$B$2:$B$18,MATCH(helper_report!$A10,src_dim_city!$A$2:$A$18,0))} -> Łódź | B24: {=INDEX(src_city_snapshot!$D$2:$D$18,MATCH(helper_report!$A10,src_city_snapshot!$A$2:$A$18,0))} -> 8019.663 | C24: {=INDEX(src_city_snapshot!$C$2:$C$18,MATCH(helper_report!$A10,src_city_snapshot!$A$2:$A$18,0))} -> 9945.4872 | D24: {=INDEX(src_city_snapshot!$K$2:$K$18,MATCH(helper_report!$A10,src_city_snapshot!$A$2:$A$18,0))} -> 24.01378 | E24: {=INDEX(src_city_snapshot!$U$2:$U$18,MATCH(helper_report!$A10,src_city_snapshot!$A$2:$A$18,0))} -> 1.1555262 | F24: {=INDEX(src_city_snapshot!$I$2:$I$18,MATCH(helper_report!$A10,src_city_snapshot!$A$2:$A$18,0))} -> 0.72083012 | G24: {=INDEX(src_city_snapshot!$AK$2:$AK$18,MATCH(helper_report!$A10,src_city_snapshot!$A$2:$A$18,0))} -> 9.0135234 | H24: =SUMIFS(src_fact_city_year!$AI$2:$AI$375,src_fact_city_year!$A$2:$A$375,helper_report!$A10,src_fact_city_year!$B$2:$B$375,src_city_snapshot!$AW$2-1) -> 2263 | I24: =SUMIFS(src_fact_city_year!$AI$2:$AI$375,src_fact_city_year!$A$2:$A$375,helper_report!$A10,src_fact_city_year!$B$2:$B$375,src_city_snapshot!$AW$2) -> 2602 | J24: =IFERROR(I24/H24-1,"") -> 0.14980115 | K24: =IF(OR(H24="",I24=""),"",I24-H24) -> 339

Sheet Methodology
A1: Methodology
A3: Definitions, reference periods, caveats and source-layer structure.
A5: 1. Metric Definitions
A6: Metric | B6: Definition | C6: Interpretation | E6: Metric | F6: Definition | G6: Interpretation
A7: Secondary Price | B7: Latest NBP secondary-market transaction price per m². | C7: Lower value = lower headline transaction price. | E7: ="H1 "&(src_city_snapshot!$AW$2-1)&" / H1 "&src_city_snapshot!$AW$2 -> H1 2025 / H1 2026 | F7: Completed dwellings from January through June. | G7: Raw counts for the current supply update.
A8: Primary Premium | B8: (Primary price / Secondary price) - 1, from the latest NBP period. | C8: Lower premium = smaller price gap between primary and secondary markets. | E8: H1 Supply Change | F8: ="H1 "&src_city_snapshot!$AW$2&" completed / H1 "&(src_city_snapshot!$AW$2-1)&" completed - 1." -> H1 2026 completed / H1 2025 completed - 1. | G8: Positive = more completions than in the same half-year a year earlier.
A9: Affordability | B9: Average monthly gross wage / annual secondary transaction price per m². | C9: Higher value = more m² equivalent to one average monthly gross wage.
A10: Price Growth | B10: Average of the latest 4 secondary-market YoY price changes. | C10: Recent price pressure; descriptive, not a forecast.
A11: Completed Supply / 1k | B11: ="Completed dwellings in "&src_city_snapshot!$AV$2&" / mid-year population × 1,000." -> Completed dwellings in 2025 / mid-year population × 1,000. | C11: Higher value = more completed dwellings relative to population.
A13: 2. Reference Periods
A14: Metric | B14: Reference period | C14: Why
A15: Secondary / Primary Price | B15: =src_city_snapshot!$AS$2 -> 2026Q2 | C15: Latest NBP price period in the frozen snapshot.
A16: Affordability | B16: =src_city_snapshot!$AT$2 -> 2025 | C16: Latest full year with wage + annual price data.
A17: Completed Supply / 1k | B17: =src_city_snapshot!$AV$2 -> 2025 | C17: Latest full-year supply; H1 2026 is not annualized.
A18: H1 Supply Change | B18: ="H1 "&src_city_snapshot!$AW$2&" vs H1 "&(src_city_snapshot!$AW$2-1) -> H1 2026 vs H1 2025 | C18: Like-for-like partial-year comparison.
A19: Price Growth | B19: ="Latest 4 NBP YoY periods through "&src_city_snapshot!$AS$2 -> Latest 4 NBP YoY periods through 2026Q2 | C19: Reduces dependence on a single YoY observation.
A21: 3. Caveats & Reporting Rules
A22: • Affordability is a proxy, not mortgage affordability or a full cost-of-living measure.
A23: ="• H1 "&src_city_snapshot!$AW$2&" is partial-year data and is compared only with H1 "&(src_city_snapshot!$AW$2-1)&"; it is not mechanically annualized." -> • H1 2026 is partial-year data and is compared only with H1 2025; it is not mechanically annualized.
A24: • Annual NBP prices require all 4 observations; incomplete years remain blank.
A25: • No composite city score is used; each comparison is based on one metric.
A26: • Different metrics intentionally use different reference periods because sources update at different frequencies.
A29: 4. Source Layer — hidden reporting CSV tabs
A30: Sheet | B30: Rows | C30: Purpose | E30: Workflow: Python cleaning / reporting exports → hidden src_* CSV tabs → spreadsheet formulas → report. The source tabs remain in the workbook for audit and lineage, but are hidden from the normal presentation view. helper_report is also hidden and exists only for display ordering and chart sorting.
A31: src_city_snapshot | B31: 17 | C31: Latest city-level reporting snapshot used by KPI and comparison metrics.
A32: src_dim_city | B32: 17 | C32: 17-city dimension and labels.
A33: src_dim_nbp_period | B33: 80 | C33: NBP period dimension.
A34: src_dim_year | B34: 22 | C34: Year dimension.
A35: src_fact_city_year | B35: 374 | C35: Annual city facts, including H1 supply fields.
A36: src_fact_hedonic_period | B36: 1200 | C36: Hedonic reporting fact retained for lineage/future extension.
A37: src_fact_price_period | B37: 1360 | C37: Period-level price fact retained for lineage/future extension.

Sheet src_city_snapshot
A1: city_id | B1: nbp_period_id | C1: primary_transaction_price_pln_m2 | D1: secondary_transaction_price_pln_m2 | E1: primary_transaction_yoy_pct | F1: primary_yoy_4p_avg_pct | G1: primary_momentum_change_pp | H1: secondary_transaction_yoy_pct | I1: secondary_yoy_4p_avg_pct | J1: secondary_momentum_change_pp | K1: primary_secondary_premium_pct | L1: primary_transaction_methodology_break | M1: primary_transaction_methodology_note | N1: primary_premium_historical_median_pct | O1: primary_premium_historical_min_pct | P1: primary_premium_historical_max_pct | Q1: avg_gross_monthly_wage_pln | R1: primary_annual_transaction_price_pln_m2 | S1: secondary_annual_transaction_price_pln_m2 | T1: primary_affordability_m2 | U1: secondary_affordability_m2 | V1: primary_affordability_yoy_pct | W1: secondary_affordability_yoy_pct | X1: primary_annual_price_yoy_pct | Y1: secondary_annual_price_yoy_pct | Z1: wage_yoy_pct | AA1: primary_affordability_2019_m2 | AB1: secondary_affordability_2019_m2 | AC1: sold_units | AD1: sold_units_per_1000 | AE1: transactions | AF1: transactions_per_1000 | AG1: avg_sold_area_m2 | AH1: started | AI1: started_per_1000 | AJ1: completed | AK1: completed_per_1000 | AL1: started_h1 | AM1: completed_h1 | AN1: started_h1_yoy_pct | AO1: completed_h1_yoy_pct | AP1: primary_premium_vs_historical_median_pp | AQ1: primary_affordability_change_since_2019_pct | AR1: secondary_affordability_change_since_2019_pct | AS1: price_reference_period | AT1: affordability_reference_year | AU1: market_activity_reference_year | AV1: supply_reference_year | AW1: supply_h1_reference_year | AX1: pareto_favorable_secondary | AY1: secondary_price_rank_lowest | AZ1: secondary_affordability_rank_highest | BA1: completed_supply_rank_highest | BB1: secondary_price_pressure_rank_lowest
A2: 1 | B2: 20262 | C2: 10926.219 | D2: 9403.1318 | E2: 4.485637 | F2: 1.9246065 | G2: -8.1815324 | H2: -0.1766421 | I2: 0.65780585 | J2: -13.318624 | K2: 16.197656 | L2: FALSE | N2: 13.395127 | O2: -1.5217602 | P2: 24.387882 | Q2: 9090.46 | R2: 10348.073 | S2: 9479.3216 | T2: 0.87846883 | U2: 0.95897791 | V2: 7.6195479 | W2: 2.577457 | X2: 1.9917958 | Y2: 7.0050992 | Z2: 9.7631096 | AA2: 0.85045897 | AB2: 0.91545854 | AC2: 4402 | AD2: 15.131984 | AE2: 4395 | AF2: 15.107921 | AG2: 49.156293 | AH2: 1891 | AI2: 6.5277802 | AJ2: 1693 | AK2: 5.8442791 | AL2: 1351 | AM2: 311 | AN2: 6.9675376 | AO2: -72.232143 | AP2: 2.8025289 | AQ2: 3.293499 | AR2: 4.7538328 | AS2: 2026Q2 | AT2: 2025 | AU2: 2024 | AV2: 2025 | AW2: 2026 | AX2: TRUE | AY2: 9 | AZ2: 9 | BA2: 12 | BB2: 4
A3: 2 | B3: 20262 | C3: 10774.886 | D3: 8341.8674 | E3: 10.450538 | F3: 13.545044 | G3: 6.4740335 | H3: 6.8922016 | I3: 1.864496 | J3: -3.2718332 | K3: 29.166357 | L3: FALSE | N3: 25.947045 | O3: -1.2833677 | P3: 41.9866 | Q3: 9219.1 | R3: 9950.4314 | S3: 7782.5 | T3: 0.92650254 | U3: 1.1845936 | V3: 0.21125594 | W3: 8.8021319 | X3: 8.8945869 | Y3: 0.29641085 | Z3: 9.1246332 | AA3: 0.81375246 | AB3: 1.007286 | AC3: 4328 | AD3: 13.317579 | AG3: 49.421858 | AH3: 1756 | AI3: 5.4455691 | AJ3: 1178 | AK3: 3.653121 | AL3: 539 | AM3: 985 | AN3: 21.396396 | AO3: 185.50725 | AP3: 3.2193112 | AQ3: 13.855575 | AR3: 17.602517 | AS3: 2026Q2 | AT3: 2025 | AU3: 2024 | AV3: 2025 | AW3: 2026 | AX3: FALSE | AY3: 4 | AZ3: 2 | BA3: 14 | BB3: 11
A4: 3 | B4: 20262 | C4: 14490.615 | D4: 14034.642 | E4: 2.897908 | F4: 7.6107044 | G4: -0.55098668 | H4: 4.6129284 | I4: 4.4716399 | J4: -5.9369519 | K4: 3.248908 | L4: FALSE | N4: 6.9606972 | O4: -5.1678116 | P4: 34.877085 | Q4: 10972.26 | R4: 14142.416 | S4: 13363.95 | T4: 0.77584054 | U4: 0.82103419 | V4: -1.3986052 | W4: 3.0119394 | X4: 10.097388 | Y4: 5.3834739 | Z4: 8.5575603 | AA4: 0.73114061 | AB4: 0.79462143 | AC4: 10037 | AD4: 20.574622 | AE4: 9985 | AF4: 20.468028 | AG4: 53.412374 | AH4: 5337 | AI4: 10.910541 | AJ4: 5750 | AK4: 11.754845 | AL4: 3109 | AM4: 1618 | AN4: -17.664195 | AO4: -26.253418 | AP4: -3.7117893 | AQ4: 6.1137253 | AR4: 3.3239428 | AS4: 2026Q2 | AT4: 2025 | AU4: 2024 | AV4: 2025 | AW4: 2026 | AX4: FALSE | AY4: 15 | AZ4: 14 | BA4: 2 | BB4: 16
A5: 4 | B5: 20262 | C5: 12886.982 | D5: 12266.795 | E5: -0.87120334 | F5: 3.173484 | G5: -5.8322325 | H5: 3.8913057 | I5: 1.4936952 | J5: -10.711979 | K5: 5.0558178 | L5: FALSE | N5: 16.721063 | O5: -1.0984939 | P5: 39.905509 | Q5: 9795.07 | R5: 13246.877 | S5: 11784.179 | T5: 0.73942486 | U5: 0.83120516 | V5: 4.7349712 | W5: 5.3520761 | X5: 3.9232901 | Y5: 3.3145545 | Z5: 8.844028 | AA5: 0.69183502 | AB5: 0.7973347 | AC5: 2676 | AD5: 11.124321 | AG5: 55.693199 | AH5: 1786 | AI5: 7.4626554 | AJ5: 864 | AK5: 3.6101536 | AL5: 1533 | AM5: 247 | AN5: 376.08696 | AO5: -16.554054 | AP5: -11.665246 | AQ5: 6.8787846 | AR5: 4.24796 | AS5: 2026Q2 | AT5: 2025 | AU5: 2024 | AV5: 2025 | AW5: 2026 | AX5: FALSE | AY5: 13 | AZ5: 13 | BA5: 16 | BB5: 9
A6: 5 | B6: 20262 | C6: 11840.15 | D6: 8101.6961 | E6: 0.83319736 | F6: 0.32336118 | G6: -12.632607 | H6: -0.64473768 | I6: 1.4105917 | J6: -8.1645658 | K6: 46.144085 | L6: FALSE | N6: 43.830588 | O6: 26.716879 | P6: 84.68385 | Q6: 10801.86 | R6: 11885.467 | S6: 8160.5898 | T6: 0.90882922 | U6: 1.3236617 | V6: 3.8864769 | W6: 2.6643376 | X6: 3.4443847 | Y6: 4.6758098 | Z6: 7.4647268 | AA6: 0.93432366 | AB6: 1.3302382 | AC6: 5565 | AD6: 20.011507 | AE6: 5710 | AF6: 20.532921 | AG6: 52.781366 | AH6: 3291 | AI6: 11.843071 | AJ6: 2334 | AK6: 8.3991882 | AL6: 1532 | AM6: 1420 | AN6: -34.107527 | AO6: 11.899133 | AP6: 2.3134978 | AQ6: -2.728651 | AR6: -0.49438851 | AS6: 2026Q2 | AT6: 2025 | AU6: 2024 | AV6: 2025 | AW6: 2026 | AX6: TRUE | AY6: 2 | AZ6: 1 | BA6: 9 | BB6: 6
A7: 6 | B7: 20262 | C7: 10401.899 | D7: 8192.6461 | E7: 7.6651442 | F7: 3.37887 | G7: -10.780715 | H7: 2.2291938 | I7: 1.4904394 | J7: -10.731231 | K7: 26.966291 | L7: FALSE | N7: 21.73071 | O7: -17.532161 | P7: 34.436147 | Q7: 9008.73 | R7: 9900.4246 | S7: 8111.7662 | T7: 0.9099337 | U7: 1.1105757 | V7: 4.6591188 | W7: 6.0502824 | X7: 4.8009234 | Y7: 3.4261489 | Z7: 9.683723 | AA7: 0.95042047 | AB7: 1.1634442 | AC7: 2227 | AD7: 12.289541 | AG7: 51.047149 | AH7: 1120 | AI7: 6.232818 | AJ7: 1045 | AK7: 5.8154418 | AL7: 785 | AM7: 493 | AN7: 56.374502 | AO7: -16.013629 | AP7: 5.2355805 | AQ7: -4.2598796 | AR7: -4.5441412 | AS7: 2026Q2 | AT7: 2025 | AU7: 2024 | AV7: 2025 | AW7: 2026 | AX7: FALSE | AY7: 3 | AZ7: 5 | BA7: 13 | BB7: 8
A8: 7 | B8: 20262 | C8: 15922.877 | D8: 14791.951 | E8: 1.4105937 | F8: -0.48398421 | G8: -14.051941 | H8: -1.1093816 | I8: -1.084829 | J8: -15.53447 | K8: 7.6455528 | L8: FALSE | N8: 4.8459127 | O8: -3.0124034 | P8: 38.304791 | Q8: 11419.23 | R8: 15644.821 | S8: 14999.031 | T8: 0.7299048 | U8: 0.76133116 | V8: 7.5442839 | W8: 7.0720905 | X8: 1.5563712 | Y8: 2.0042399 | Z8: 9.2180721 | AA8: 0.75391801 | AB8: 0.76449358 | AC8: 15120 | AD8: 18.72112 | AE8: 14770 | AF8: 18.28776 | AG8: 52.232196 | AH8: 7962 | AI8: 9.822475 | AJ8: 7946 | AK8: 9.8027363 | AL8: 3573 | AM8: 4501 | AN8: -33.992241 | AO8: 64.811424 | AP8: 2.7996401 | AQ8: -3.185122 | AR8: -0.41366186 | AS8: 2026Q2 | AT8: 2025 | AU8: 2024 | AV8: 2025 | AW8: 2026 | AX8: FALSE | AY8: 16 | AZ8: 16 | BA8: 6 | BB8: 2
A9: 8 | B9: 20262 | C9: 10889.14 | D9: 10219.03 | E9: -0.8114248 | F9: 0.043194192 | G9: -10.281055 | H9: 2.0496755 | I9: 1.9584294 | J9: -9.8947007 | K9: 6.5574717 | L9: FALSE | N9: 6.5194613 | O9: -11.50286 | P9: 18.921888 | Q9: 9288.09 | R9: 11002.312 | S9: 10021.665 | T9: 0.84419435 | U9: 0.92680109 | V9: 5.441238 | W9: 4.0925891 | X9: 3.5416263 | Y9: 4.8831367 | Z9: 9.1755726 | AA9: 0.8473803 | AB9: 0.90298413 | AC9: 5644 | AD9: 17.161901 | AG9: 50.998051 | AH9: 2155 | AI9: 6.5824842 | AJ9: 2907 | AK9: 8.879481 | AL9: 1433 | AM9: 1433 | AN9: 10.999225 | AO9: 53.426124 | AP9: 0.038010376 | AQ9: -0.37597719 | AR9: 2.6375828 | AS9: 2026Q2 | AT9: 2025 | AU9: 2024 | AV9: 2025 | AW9: 2026 | AX9: FALSE | AY9: 10 | AZ9: 11 | BA9: 8 | BB9: 12
A10: 9 | B10: 20262 | C10: 10680.51 | D10: 8940.509 | E10: 6.849218 | F10: 8.9043256 | G10: 0.27523846 | H10: 5.2766753 | I10: 3.8693641 | J10: -6.8059028 | K10: 19.46199 | L10: FALSE | N10: 12.030251 | O10: -29.798133 | P10: 28.917279 | Q10: 9304.52 | R10: 10043.432 | S10: 8614.2537 | T10: 0.92642829 | U10: 1.0801307 | V10: -1.3537493 | W10: 2.9348263 | X10: 9.5071065 | Y10: 4.9447098 | Z10: 8.0246548 | AA10: 0.86409653 | AB10: 0.98147459 | AC10: 2646 | AD10: 15.873111 | AE10: 2696 | AF10: 16.173057 | AG10: 51.587302 | AH10: 1092 | AI10: 6.5840644 | AJ10: 600 | AK10: 3.6176178 | AL10: 336 | AM10: 778 | AN10: -50.148368 | AO10: 298.97436 | AP10: 7.4317394 | AQ10: 7.2135181 | AR10: 10.051826 | AS10: 2026Q2 | AT10: 2025 | AU10: 2024 | AV10: 2025 | AW10: 2026 | AX10: FALSE | AY10: 6 | AZ10: 6 | BA10: 15 | BB10: 14
A11: 10 | B11: 20262 | C11: 11624.601 | D11: 9215.2766 | E11: 5.3213776 | F11: 3.7925396 | G11: -5.8793153 | H11: 5.3587302 | I11: 3.8899978 | J11: -8.3784712 | K11: 26.144899 | L11: FALSE | N11: 15.514617 | O11: -14.369936 | P11: 30.892219 | Q11: 9465.22 | R11: 11166.636 | S11: 8880.8649 | T11: 0.84763398 | U11: 1.0657993 | V11: 2.9300331 | W11: 4.9723577 | X11: 7.3762894 | Y11: 5.2871942 | Z11: 10.52245 | AA11: 0.94706608 | AB11: 1.0476436 | AC11: 1500 | AD11: 11.922551 | AE11: 1499 | AF11: 11.914603 | AG11: 53.374667 | AH11: 686 | AI11: 5.4838323 | AJ11: 365 | AK11: 2.9177825 | AL11: 277 | AM11: 323 | AN11: 53.888889 | AO11: 95.757576 | AP11: 10.630283 | AQ11: -10.498962 | AR11: 1.7330119 | AS11: 2026Q2 | AT11: 2025 | AU11: 2024 | AV11: 2025 | AW11: 2026 | AX11: FALSE | AY11: 7 | AZ11: 8 | BA11: 17 | BB11: 15
A12: 11 | B12: 20262 | C12: 12765.859 | D12: 10890.792 | E12: 2.4374453 | F12: 1.824535 | G12: -6.2103661 | H12: 0.094648207 | I12: 1.6999744 | J12: -9.1373288 | K12: 17.216996 | L12: FALSE | N12: 17.325584 | O12: -6.0297149 | P12: 50.975229 | Q12: 10294.78 | R12: 12441.147 | S12: 10931.782 | T12: 0.82747836 | U12: 0.94172939 | V12: 6.2773026 | W12: 3.8267553 | X12: 2.018369 | Y12: 4.4262343 | Z12: 8.4223708 | AA12: 0.79791403 | AB12: 0.90112246 | AC12: 9744 | AD12: 18.151403 | AE12: 9583 | AF12: 17.851488 | AG12: 52.883754 | AH12: 3130 | AI12: 5.8514188 | AJ12: 5608 | AK12: 10.483948 | AL12: 2515 | AM12: 2319 | AN12: 31.813417 | AO12: 29.480737 | AP12: -0.1085886 | AQ12: 3.705202 | AR12: 4.506262 | AS12: 2026Q2 | AT12: 2025 | AU12: 2024 | AV12: 2025 | AW12: 2026 | AX12: TRUE | AY12: 11 | AZ12: 10 | BA12: 5 | BB12: 10
A13: 12 | B13: 20262 | C13: 10329.021 | D13: 10973.994 | E13: -3.9940305 | F13: 1.3220909 | G13: -8.3929357 | H13: 2.364589 | I13: 1.9723635 | J13: -12.982477 | K13: -5.8772826 | L13: FALSE | N13: -0.09752964 | O13: -12.874421 | P13: 12.00577 | Q13: 9537.56 | R13: 10344.724 | S13: 10664.115 | T13: 0.92197341 | U13: 0.89436017 | V13: 4.4102323 | W13: 3.5384548 | X13: 5.2325223 | Y13: 6.1185635 | Z13: 9.873521 | AA13: 0.90949258 | AB13: 0.93423356 | AC13: 3574 | AD13: 18.077347 | AG13: 53.037633 | AH13: 1824 | AI13: 9.1870656 | AJ13: 3097 | AK13: 15.598872 | AL13: 1942 | AM13: 1526 | AN13: 75.905797 | AO13: -10.968495 | AP13: -5.779753 | AQ13: 1.3722847 | AR13: -4.268033 | AS13: 2026Q2 | AT13: 2025 | AU13: 2024 | AV13: 2025 | AW13: 2026 | AX13: TRUE | AY13: 12 | AZ13: 12 | BA13: 1 | BB13: 13
A14: 13 | B14: 20262 | C14: 11427.47 | D14: 9363.2163 | E14: -1.9058343 | F14: -2.3432434 | G14: -6.9045901 | H14: 1.7194855 | I14: 1.4283439 | J14: -7.2153418 | K14: 22.046419 | L14: FALSE | N14: 22.690182 | O14: 2.7567428 | P14: 49.518392 | Q14: 9908.84 | R14: 11765.397 | S14: 9265.1093 | T14: 0.84220196 | U14: 1.069479 | V14: 11.012717 | W14: 7.0384349 | X14: -1.3134793 | Y14: 2.3507006 | Z14: 9.554588 | AA14: 0.8367337 | AB14: 1.0237544 | AC14: 2224 | AD14: 5.7363941 | AG14: 55.084083 | AH14: 2109 | AI14: 5.4756749 | AJ14: 2380 | AK14: 6.1792823 | AL14: 2691 | AM14: 680 | AN14: 97.722263 | AO14: -29.240375 | AP14: -0.64376359 | AQ14: 0.65352465 | AR14: 4.4663676 | AS14: 2026Q2 | AT14: 2025 | AU14: 2024 | AV14: 2025 | AW14: 2026 | AX14: FALSE | AY14: 8 | AZ14: 7 | BA14: 11 | BB14: 7
A15: 14 | B15: 20262 | C15: 16783.491 | D15: 16722.657 | E15: 2.4213367 | F15: 0.65029658 | G15: -7.6346864 | H15: 1.3051898 | I15: -0.82738646 | J15: -14.193609 | K15: 0.36378587 | L15: FALSE | N15: -0.25266953 | O15: -12.082684 | P15: 5.9181201 | Q15: 11687.95 | R15: 16422.89 | S15: 16598.228 | T15: 0.71168656 | U15: 0.70416855 | V15: 7.5130633 | W15: 7.3400296 | X15: 1.4577762 | Y15: 1.6213276 | Z15: 9.0803631 | AA15: 0.74820683 | AB15: 0.72880252 | AC15: 24395 | AD15: 13.098676 | AE15: 24405 | AF15: 13.104045 | AG15: 57.027465 | AH15: 14399 | AI15: 7.7246404 | AJ15: 19844 | AK15: 10.645723 | AL15: 6528 | AM15: 6867 | AN15: -6.7828074 | AO15: -17.26506 | AP15: 0.6164554 | AQ15: -4.8810398 | AR15: -3.3800613 | AS15: 2026Q2 | AT15: 2025 | AU15: 2024 | AV15: 2025 | AW15: 2026 | AX15: FALSE | AY15: 17 | AZ15: 17 | BA15: 4 | BB15: 3
A16: 15 | B16: 20262 | C16: 14312.254 | D16: 12589.783 | E16: -4.7119982 | F16: -2.2731327 | G16: -17.491448 | H16: -0.2789898 | I16: -1.3611285 | J16: -11.091895 | K16: 13.681501 | L16: FALSE | N16: 8.3350317 | O16: -26.411446 | P16: 25.014636 | Q16: 10155.68 | R16: 14466.83 | S16: 12599.897 | T16: 0.70199758 | U16: 0.80601293 | V16: 2.8584696 | W16: 6.9500482 | X16: 4.755316 | Y16: 0.74770109 | Z16: 7.7497149 | AA16: 0.77380908 | AB16: 0.85041982 | AC16: 13194 | AD16: 19.589299 | AE16: 13958 | AF16: 20.723619 | AG16: 54.26246 | AH16: 5009 | AI16: 7.4478288 | AJ16: 7700 | AK16: 11.449048 | AL16: 2657 | AM16: 3182 | AN16: 1.2190476 | AO16: -8.5894858 | AP16: 5.346469 | AQ16: -9.2802601 | AR16: -5.2217607 | AS16: 2026Q2 | AT16: 2025 | AU16: 2024 | AV16: 2025 | AW16: 2026 | AX16: TRUE | AY16: 14 | AZ16: 15 | BA16: 3 | BB16: 1
A17: 16 | B17: 20262 | C17: 9457.8511 | D17: 8633.384 | E17: -0.81968429 | F17: 3.2157533 | G17: -12.551759 | H17: 6.9108333 | I17: 7.7493366 | J17: -4.9999276 | K17: 9.549755 | L17: FALSE | N17: 16.814756 | O17: 2.2536824 | P17: 27.985763 | Q17: 9302.48 | R17: 9350.7537 | S17: 8348.1411 | T17: 0.99483746 | U17: 1.1143175 | V17: -4.8012384 | W17: -0.52913472 | X17: 12.577532 | Y17: 7.7425194 | Z17: 7.1724163 | AA17: 1.0894957 | AB17: 1.1731235 | AC17: 1789 | AD17: 12.880975 | AG17: 56.082057 | AH17: 842 | AI17: 6.0680311 | AJ17: 1063 | AK17: 7.6607091 | AL17: 464 | AM17: 296 | AN17: -17.290553 | AO17: -25.440806 | AP17: -7.2650007 | AQ17: -8.6882634 | AR17: -5.0127709 | AS17: 2026Q2 | AT17: 2025 | AU17: 2024 | AV17: 2025 | AW17: 2026 | AX17: FALSE | AY17: 5 | AZ17: 4 | BA17: 10 | BB17: 17
A18: 17 | B18: 20262 | C18: 9945.4872 | D18: 8019.663 | E18: -1.0520383 | F18: -1.3342873 | G18: -6.4062736 | H18: -1.6521647 | I18: 0.72083012 | J18: -9.3490704 | K18: 24.01378 | L18: FALSE | N18: 27.586184 | O18: 13.04299 | P18: 62.860375 | Q18: 9374.53 | R18: 9844.4548 | S18: 8112.7801 | T18: 0.95226503 | U18: 1.1555262 | V18: 10.518097 | W18: 4.5798898 | X18: -1.6170881 | Y18: 3.969245 | Z18: 8.7309218 | AA18: 0.88492839 | AB18: 1.0856449 | AC18: 9633 | AD18: 14.849448 | AE18: 9679 | AF18: 14.920357 | AG18: 48.667892 | AH18: 7520 | AI18: 11.702641 | AJ18: 5792 | AK18: 9.0135234 | AL18: 3182 | AM18: 2602 | AN18: -27.118644 | AO18: 14.980115 | AP18: -3.5724042 | AQ18: 7.609275 | AR18: 6.4368517 | AS18: 2026Q2 | AT18: 2025 | AU18: 2024 | AV18: 2025 | AW18: 2026 | AX18: TRUE | AY18: 1 | AZ18: 3 | BA18: 7 | BB18: 5

Sheet src_dim_city
A1: city_id | B1: city_name | C1: teryt_code | D1: gus_name
A2: 1 | B2: Białystok | C2: 2061000 | D2: Powiat m. Białystok
A3: 2 | B3: Bydgoszcz | C3: 0461000 | D3: Powiat m. Bydgoszcz
A4: 3 | B4: Gdańsk | C4: 2261000 | D4: Powiat m. Gdańsk
A5: 4 | B5: Gdynia | C5: 2262000 | D5: Powiat m. Gdynia
A6: 5 | B6: Katowice | C6: 2469000 | D6: Powiat m. Katowice
A7: 6 | B7: Kielce | C7: 2661000 | D7: Powiat m. Kielce
A8: 7 | B8: Kraków | C8: 1261000 | D8: Powiat m. Kraków
A9: 8 | B9: Lublin | C9: 0663000 | D9: Powiat m. Lublin
A10: 9 | B10: Olsztyn | C10: 2862000 | D10: Powiat m. Olsztyn
A11: 10 | B11: Opole | C11: 1661000 | D11: Powiat m. Opole
A12: 11 | B12: Poznań | C12: 3064000 | D12: Powiat m. Poznań
A13: 12 | B13: Rzeszów | C13: 1863000 | D13: Powiat m. Rzeszów
... A18: 17 | B18: Łódź | C18: 1061000 | D18: Powiat m. Łódź

Sheet src_dim_nbp_period
A1: nbp_period_id | B1: nbp_period | C1: nbp_year | D1: nbp_quarter
A2: 20063 | B2: 2006Q3 | C2: 2006 | D2: 3
A3: 20064 | B3: 2006Q4 | C3: 2006 | D3: 4
A4: 20071 | B4: 2007Q1 | C4: 2007 | D4: 1
A5: 20072 | B5: 2007Q2 | C5: 2007 | D5: 2
A6: 20073 | B6: 2007Q3 | C6: 2007 | D6: 3
A7: 20074 | B7: 2007Q4 | C7: 2007 | D7: 4
A8: 20081 | B8: 2008Q1 | C8: 2008 | D8: 1
A9: 20082 | B9: 2008Q2 | C9: 2008 | D9: 2
A10: 20083 | B10: 2008Q3 | C10: 2008 | D10: 3
A11: 20084 | B11: 2008Q4 | C11: 2008 | D11: 4
A12: 20091 | B12: 2009Q1 | C12: 2009 | D12: 1
A13: 20092 | B13: 2009Q2 | C13: 2009 | D13: 2
... A81: 20262 | B81: 2026Q2 | C81: 2026 | D81: 2

Sheet src_dim_year
A1: year
A2: 2005
A3: 2006
A4: 2007
A5: 2008
A6: 2009
A7: 2010
A8: 2011
A9: 2012
A10: 2013
A11: 2014
A12: 2015
A13: 2016
... A23: 2026

Sheet src_fact_city_year
A1: city_id | B1: year | C1: avg_gross_monthly_wage_pln | D1: population_mid_year | E1: primary_annual_transaction_price_pln_m2 | F1: secondary_annual_transaction_price_pln_m2 | G1: primary_price_quarters_available | H1: secondary_price_quarters_available | I1: primary_affordability_m2 | J1: primary_annual_price_yoy_pct | K1: primary_affordability_yoy_pct | L1: secondary_affordability_m2 | M1: secondary_annual_price_yoy_pct | N1: secondary_affordability_yoy_pct | O1: wage_yoy_pct | P1: transactions | Q1: transaction_quarters_available | R1: sold_units | S1: sold_units_quarters_available | T1: sold_area_m2 | U1: sold_area_quarters_available | V1: avg_sold_area_m2 | W1: transactions_full_year_available | X1: sold_units_full_year_available | Y1: transactions_per_1000 | Z1: sold_units_per_1000 | AA1: completed | AB1: started | AC1: completed_months_available | AD1: started_months_available | AE1: started_full_year_available | AF1: completed_full_year_available | AG1: started_per_1000 | AH1: completed_per_1000 | AI1: completed_h1 | AJ1: started_h1 | AK1: completed_h1_months_available | AL1: started_h1_months_available | AM1: started_h1_yoy_pct | AN1: completed_h1_yoy_pct
A2: 1 | B2: 2005 | C2: 2365 | D2: 292138 | AA2: 1225 | AB2: 1338 | AC2: 12 | AD2: 12 | AE2: TRUE | AF2: TRUE | AG2: 4.5800272 | AH2: 4.1932238 | AI2: 383 | AJ2: 386 | AK2: 6 | AL2: 6
A3: 1 | B3: 2006 | C3: 2478.96 | D3: 295210 | AA3: 1219 | AB3: 1850 | AC3: 12 | AD3: 12 | AE3: TRUE | AF3: TRUE | AG3: 6.2667254 | AH3: 4.1292639 | AI3: 496 | AJ3: 540 | AK3: 6 | AL3: 6 | AM3: 39.896373 | AN3: 29.503916
A4: 1 | B4: 2007 | C4: 2715.96 | D4: 294817 | E4: 4413 | F4: 4029.6579 | G4: 4 | H4: 4 | I4: 0.61544528 | L4: 0.6739927 | AA4: 1667 | AB4: 1722 | AC4: 12 | AD4: 12 | AE4: TRUE | AF4: TRUE | AG4: 5.8409115 | AH4: 5.6543551 | AI4: 402 | AJ4: 608 | AK4: 6 | AL4: 6 | AM4: 12.592593 | AN4: -18.951613
A5: 1 | B5: 2008 | C5: 2994.05 | D5: 294265 | E5: 5112.75 | F5: 4410.5093 | G5: 4 | H5: 4 | I5: 0.58560462 | J5: 15.85656 | K5: -4.8486292 | L5: 0.67884451 | M5: 9.4512093 | N5: 0.71986029 | O5: 10.239105 | AA5: 1574 | AB5: 2058 | AC5: 12 | AD5: 12 | AE5: TRUE | AF5: TRUE | AG5: 6.9936962 | AH5: 5.3489202 | AI5: 628 | AJ5: 675 | AK5: 6 | AL5: 6 | AM5: 11.019737 | AN5: 56.218905
A6: 1 | B6: 2009 | C6: 3144.6 | D6: 294399 | E6: 4901.5 | F6: 4043.3258 | G6: 4 | H6: 4 | I6: 0.64155871 | J6: -4.1318273 | K6: 9.5549265 | L6: 0.7777261 | M6: -8.3251941 | N6: 14.566161 | O6: 5.0283061 | AA6: 1533 | AB6: 1300 | AC6: 12 | AD6: 12 | AE6: TRUE | AF6: TRUE | AG6: 4.4157759 | AH6: 5.2072188 | AI6: 483 | AJ6: 345 | AK6: 6 | AL6: 6 | AM6: -48.888889 | AN6: -23.089172
A7: 1 | B7: 2010 | C7: 3241.41 | D7: 293946 | E7: 4769.75 | F7: 4150.916 | G7: 4 | H7: 4 | I7: 0.6795765 | J7: -2.6879527 | K7: 5.9258476 | L7: 0.78089028 | M7: 2.660934 | N7: 0.40685095 | O7: 3.078611 | P7: 1491 | Q7: 4 | R7: 1496 | S7: 4 | T7: 80612.1 | U7: 4 | V7: 53.885094 | W7: TRUE | X7: TRUE | Y7: 5.0723602 | Z7: 5.0893702 | AA7: 1630 | AB7: 2075 | AC7: 12 | AD7: 12 | AE7: TRUE | AF7: TRUE | AG7: 7.0591197 | AH7: 5.5452362 | AI7: 736 | AJ7: 578 | AK7: 6 | AL7: 6 | AM7: 67.536232 | AN7: 52.380952
A8: 1 | B8: 2011 | C8: 3360.36 | D8: 294197 | E8: 4761.75 | F8: 4308.5613 | G8: 4 | H8: 4 | I8: 0.70569854 | J8: -0.16772368 | K8: 3.8438701 | L8: 0.77992624 | M8: 3.7978422 | N8: -0.1234543 | O8: 3.6696993 | P8: 1766 | Q8: 4 | R8: 1822 | S8: 4 | T8: 98722.1 | U8: 4 | V8: 54.18337 | W8: TRUE | X8: TRUE | Y8: 6.0027804 | Z8: 6.1931291 | AA8: 1711 | AB8: 1191 | AC8: 12 | AD8: 12 | AE8: TRUE | AF8: TRUE | AG8: 4.0483078 | AH8: 5.8158309 | AI8: 592 | AJ8: 485 | AK8: 6 | AL8: 6 | AM8: -16.089965 | AN8: -19.565217
A9: 1 | B9: 2012 | C9: 3493.98 | D9: 294675 | E9: 4456.25 | F9: 4050.3847 | G9: 4 | H9: 4 | I9: 0.78406283 | J9: -6.4157085 | K9: 11.104501 | L9: 0.86262917 | M9: -5.9921764 | N9: 10.603943 | O9: 3.9763597 | P9: 2045 | Q9: 4 | R9: 2056 | S9: 4 | T9: 107206.3 | U9: 4 | V9: 52.143142 | W9: TRUE | X9: TRUE | Y9: 6.939849 | Z9: 6.9771782 | AA9: 2249 | AB9: 2013 | AC9: 12 | AD9: 12 | AE9: TRUE | AF9: TRUE | AG9: 6.8312548 | AH9: 7.6321371 | AI9: 1074 | AJ9: 1148 | AK9: 6 | AL9: 6 | AM9: 136.70103 | AN9: 81.418919
A10: 1 | B10: 2013 | C10: 3627.02 | D10: 294925 | E10: 4514.25 | F10: 3900.7926 | G10: 4 | H10: 4 | I10: 0.80346015 | J10: 1.3015428 | K10: 2.4739498 | L10: 0.92981617 | M10: -3.6932821 | N10: 7.7886303 | O10: 3.8076921 | P10: 2090 | Q10: 4 | R10: 2069 | S10: 4 | T10: 108305.7 | U10: 4 | V10: 52.346883 | W10: TRUE | X10: TRUE | Y10: 7.0865474 | Z10: 7.0153429 | AA10: 1574 | AB10: 1324 | AC10: 12 | AD10: 12 | AE10: TRUE | AF10: TRUE | AG10: 4.4892769 | AH10: 5.3369501 | AI10: 403 | AJ10: 643 | AK10: 6 | AL10: 6 | AM10: -43.989547 | AN10: -62.476723
A11: 1 | B11: 2014 | C11: 3706.73 | D11: 295401 | E11: 4497.5 | F11: 3935.4661 | G11: 4 | H11: 4 | I11: 0.82417565 | J11: -0.37104724 | K11: 2.5782858 | L11: 0.94187827 | M11: 0.88888483 | N11: 1.297256 | O11: 2.1976719 | P11: 2399 | Q11: 4 | R11: 2412 | S11: 4 | T11: 122371.3 | U11: 4 | V11: 50.73437 | W11: TRUE | X11: TRUE | Y11: 8.1211641 | Z11: 8.1651721 | AA11: 1736 | AB11: 2031 | AC11: 12 | AD11: 12 | AE11: TRUE | AF11: TRUE | AG11: 6.8753999 | AH11: 5.8767574 | AI11: 860 | AJ11: 699 | AK11: 6 | AL11: 6 | AM11: 8.7091757 | AN11: 113.3995
A12: 1 | B12: 2015 | C12: 3844.68 | D12: 295624 | E12: 4566 | F12: 3928.0467 | G12: 4 | H12: 4 | I12: 0.84202365 | J12: 1.5230684 | K12: 2.1655578 | L12: 0.97877655 | M12: -0.18852686 | N12: 3.9175215 | O12: 3.7216091 | P12: 2441 | Q12: 4 | R12: 2448 | S12: 4 | T12: 121826.8 | U12: 4 | V12: 49.76585 | W12: TRUE | X12: TRUE | Y12: 8.2571104 | Z12: 8.2807891 | AA12: 2088 | AB12: 1893 | AC12: 12 | AD12: 12 | AE12: TRUE | AF12: TRUE | AG12: 6.4034043 | AH12: 7.063026 | AI12: 915 | AJ12: 359 | AK12: 6 | AL12: 6 | AM12: -48.640916 | AN12: 6.3953488
A13: 1 | B13: 2016 | C13: 3967.71 | D13: 296310 | E13: 4577.5 | F13: 3989.9963 | G13: 4 | H13: 4 | I13: 0.86678536 | J13: 0.25186159 | K13: 2.9407381 | L13: 0.99441446 | M13: 1.5771094 | N13: 1.5976994 | O13: 3.2000062 | P13: 2869 | Q13: 4 | R13: 2864 | S13: 4 | T13: 142836.3 | U13: 4 | V13: 49.87301 | W13: TRUE | X13: TRUE | Y13: 9.6824272 | Z13: 9.665553 | AA13: 1795 | AB13: 1514 | AC13: 12 | AD13: 12 | AE13: TRUE | AF13: TRUE | AG13: 5.1095137 | AH13: 6.0578448 | AI13: 875 | AJ13: 409 | AK13: 6 | AL13: 6 | AM13: 13.927577 | AN13: -4.3715847
A14: 1 | B14: 2017 | C14: 4164.59 | D14: 297132 | E14: 4587.25 | F14: 4105.502 | G14: 4 | H14: 4 | I14: 0.90786201 | J14: 0.21299836 | K14: 4.7389639 | L14: 1.0143924 | M14: 2.8948832 | N14: 2.0090144 | O14: 4.9620562 | P14: 3146 | Q14: 4 | R14: 3146 | S14: 4 | T14: 161938.1 | U14: 4 | V14: 51.474285 | W14: TRUE | X14: TRUE | Y14: 10.587887 | Z14: 10.587887 | AA14: 2033 | AB14: 2507 | AC14: 12 | AD14: 12 | AE14: TRUE | AF14: TRUE | AG14: 8.4373275 | AH14: 6.8420769 | AI14: 1086 | AJ14: 1326 | AK14: 6 | AL14: 6 | AM14: 224.20538 | AN14: 24.114286
A15: 1 | B15: 2018 | C15: 4396.32 | D15: 297403 | E15: 5183 | F15: 4552.0334 | G15: 4 | H15: 4 | I15: 0.84821918 | J15: 12.987084 | K15: -6.5695921 | L15: 0.96579257 | M15: 10.876413 | N15: -4.7910276 | O15: 5.5642932 | P15: 2982 | Q15: 4 | R15: 2992 | S15: 4 | T15: 150707.7 | U15: 4 | V15: 50.370221 | W15: TRUE | X15: TRUE | Y15: 10.026799 | Z15: 10.060423 | AA15: 1927 | AB15: 3438 | AC15: 12 | AD15: 12 | AE15: TRUE | AF15: TRUE | AG15: 11.560072 | AH15: 6.4794235 | AI15: 716 | AJ15: 1891 | AK15: 6 | AL15: 6 | AM15: 42.609351 | AN15: -34.069982
A16: 1 | B16: 2019 | C16: 4744.13 | D16: 297356 | E16: 5578.3173 | F16: 5182.2445 | G16: 4 | H16: 4 | I16: 0.85045897 | J16: 7.6271911 | K16: 0.26405823 | L16: 0.91545854 | M16: 13.844607 | N16: -5.2116808 | O16: 7.9113895 | P16: 3452 | Q16: 4 | R16: 3510 | S16: 4 | T16: 180151.7 | U16: 4 | V16: 51.325271 | W16: TRUE | X16: TRUE | Y16: 11.60898 | Z16: 11.804033 | AA16: 2450 | AB16: 2903 | AC16: 12 | AD16: 12 | AE16: TRUE | AF16: TRUE | AG16: 9.7627087 | AH16: 8.2392822 | AI16: 861 | AJ16: 2060 | AK16: 6 | AL16: 6 | AM16: 8.9370703 | AN16: 20.251397
A17: 1 | B17: 2020 | C17: 5126.79 | D17: 295302 | E17: 5823.2728 | F17: 5778.3057 | G17: 4 | H17: 4 | I17: 0.88039667 | J17: 4.3912081 | K17: 3.5201813 | L17: 0.88724796 | M17: 11.50199 | N17: -3.081579 | O17: 8.0659678 | P17: 3363 | Q17: 4 | R17: 3402 | S17: 4 | T17: 171883.9 | U17: 4 | V17: 50.524368 | W17: TRUE | X17: TRUE | Y17: 11.388341 | Z17: 11.52041 | AA17: 2832 | AB17: 3258 | AC17: 12 | AD17: 12 | AE17: TRUE | AF17: TRUE | AG17: 11.032773 | AH17: 9.5901823 | AI17: 1104 | AJ17: 1568 | AK17: 6 | AL17: 6 | AM17: -23.883495 | AN17: 28.222997
A18: 1 | B18: 2021 | C18: 5650.97 | D18: 294131 | E18: 6671.1237 | F18: 6291.392 | G18: 4 | H18: 4 | I18: 0.84707918 | J18: 14.559697 | K18: -3.7843727 | L18: 0.89820663 | M18: 8.8795273 | N18: 1.2351304 | O18: 10.224331 | P18: 4549 | Q18: 4 | R18: 4592 | S18: 4 | T18: 236576.2 | U18: 4 | V18: 51.519207 | W18: TRUE | X18: TRUE | Y18: 15.465898 | Z18: 15.612091 | AA18: 3234 | AB18: 3082 | AC18: 12 | AD18: 12 | AE18: TRUE | AF18: TRUE | AG18: 10.478324 | AH18: 10.995101 | AI18: 1440 | AJ18: 1878 | AK18: 6 | AL18: 6 | AM18: 19.770408 | AN18: 30.434783
A19: 1 | B19: 2022 | C19: 6183.98 | D19: 293028 | E19: 8338.4935 | F19: 7352.5927 | G19: 4 | H19: 4 | I19: 0.74161838 | J19: 24.993836 | K19: -12.449934 | L19: 0.84106114 | M19: 16.867502 | N19: -6.3621762 | O19: 9.432186 | P19: 3667 | Q19: 4 | R19: 3827 | S19: 4 | T19: 195585.8 | U19: 4 | V19: 51.10682 | W19: TRUE | X19: TRUE | Y19: 12.514162 | Z19: 13.060185 | AA19: 1979 | AB19: 1366 | AC19: 12 | AD19: 12 | AE19: TRUE | AF19: TRUE | AG19: 4.6616706 | AH19: 6.7536208 | AI19: 1207 | AJ19: 1071 | AK19: 6 | AL19: 6 | AM19: -42.971246 | AN19: -16.180556
A20: 1 | B20: 2023 | C20: 7089.31 | D20: 292058 | E20: 8701.2169 | F20: 7571.7266 | G20: 4 | H20: 4 | I20: 0.81474926 | J20: 4.3499871 | K20: 9.8609858 | L20: 0.93628711 | M20: 2.9803626 | N20: 11.322122 | O20: 14.639924 | Q20: 2 | R20: 3958 | S20: 4 | T20: 195474 | U20: 4 | V20: 49.387064 | W20: FALSE | X20: TRUE | Z20: 13.552103 | AA20: 2786 | AB20: 826 | AC20: 12 | AD20: 12 | AE20: TRUE | AF20: TRUE | AG20: 2.8282054 | AH20: 9.5392011 | AI20: 1633 | AJ20: 303 | AK20: 6 | AL20: 6 | AM20: -71.708683 | AN20: 35.294118
A21: 1 | B21: 2024 | C21: 8281.89 | D21: 290907 | E21: 10145.986 | F21: 8858.7569 | G21: 4 | H21: 4 | I21: 0.81627255 | J21: 16.604221 | K21: 0.18696438 | L21: 0.93488174 | M21: 16.997844 | N21: -0.15010071 | O21: 16.82223 | P21: 4395 | Q21: 4 | R21: 4402 | S21: 4 | T21: 216386 | U21: 4 | V21: 49.156293 | W21: TRUE | X21: TRUE | Y21: 15.107921 | Z21: 15.131984 | AA21: 2503 | AB21: 2855 | AC21: 12 | AD21: 12 | AE21: TRUE | AF21: TRUE | AG21: 9.814133 | AH21: 8.6041243 | AI21: 1513 | AJ21: 1229 | AK21: 6 | AL21: 6 | AM21: 305.61056 | AN21: -7.3484385
A22: 1 | B22: 2025 | C22: 9090.46 | D22: 289685 | E22: 10348.073 | F22: 9479.3216 | G22: 4 | H22: 4 | I22: 0.87846883 | J22: 1.9917958 | K22: 7.6195479 | L22: 0.95897791 | M22: 7.0050992 | N22: 2.577457 | O22: 9.7631096 | AA22: 1693 | AB22: 1891 | AC22: 12 | AD22: 12 | AE22: TRUE | AF22: TRUE | AG22: 6.5277802 | AH22: 5.8442791 | AI22: 1120 | AJ22: 1263 | AK22: 6 | AL22: 6 | AM22: 2.7664768 | AN22: -25.974884
A23: 1 | B23: 2026 | AI23: 311 | AJ23: 1351 | AK23: 6 | AL23: 6 | AM23: 6.9675376 | AN23: -72.232143
A24: 2 | B24: 2005 | C24: 2343.98 | D24: 367368 | AA24: 505 | AB24: 633 | AC24: 12 | AD24: 12 | AE24: TRUE | AF24: TRUE | AG24: 1.7230679 | AH24: 1.3746434 | AI24: 257 | AJ24: 38 | AK24: 6 | AL24: 6
A25: 2 | B25: 2006 | C25: 2482.78 | D25: 364953 | AA25: 681 | AB25: 1184 | AC25: 12 | AD25: 12 | AE25: TRUE | AF25: TRUE | AG25: 3.2442534 | AH25: 1.8659937 | AI25: 150 | AJ25: 475 | AK25: 6 | AL25: 6 | AM25: 1150 | AN25: -41.634241
A26: 2 | B26: 2007 | C26: 2690.84 | D26: 362397 | E26: 4039.25 | F26: 3634.3243 | G26: 4 | H26: 4 | I26: 0.66617318 | L26: 0.74039623 | AA26: 668 | AB26: 1243 | AC26: 12 | AD26: 12 | AE26: TRUE | AF26: TRUE | AG26: 3.4299401 | AH26: 1.8432824 | AI26: 414 | AJ26: 697 | AK26: 6 | AL26: 6 | AM26: 46.736842 | AN26: 176
A27: 2 | B27: 2008 | C27: 2973.85 | D27: 360142 | E27: 4735.25 | F27: 3841.0021 | G27: 4 | H27: 4 | I27: 0.62802386 | J27: 17.230922 | K27: -5.7266359 | L27: 0.77423806 | M27: 5.6868286 | N27: 4.5707729 | O27: 10.517534 | AA27: 1512 | AB27: 1604 | AC27: 12 | AD27: 12 | AE27: TRUE | AF27: TRUE | AG27: 4.4537988 | AH27: 4.198344 | AI27: 586 | AJ27: 1186 | AK27: 6 | AL27: 6 | AM27: 70.157819 | AN27: 41.545894
A28: 2 | B28: 2009 | C28: 3074.32 | D28: 358029 | E28: 4827.25 | F28: 3698.3685 | G28: 4 | H28: 4 | I28: 0.63686778 | J28: 1.9428752 | K28: 1.4082137 | L28: 0.83126383 | M28: -3.7134455 | N28: 7.3654046 | O28: 3.3784488 | AA28: 987 | AB28: 1131 | AC28: 12 | AD28: 12 | AE28: TRUE | AF28: TRUE | AG28: 3.158962 | AH28: 2.7567599 | AI28: 237 | AJ28: 416 | AK28: 6 | AL28: 6 | AM28: -64.924115 | AN28: -59.556314
A29: 2 | B29: 2010 | C29: 3184.45 | D29: 365202 | E29: 4735 | F29: 3809.6278 | G29: 4 | H29: 4 | I29: 0.67253432 | J29: -1.9110259 | K29: 5.6003048 | L29: 0.83589531 | M29: 3.0083334 | N29: 0.55716098 | O29: 3.5822556 | P29: 1782 | Q29: 4 | R29: 1595 | S29: 4 | T29: 83987.9 | U29: 4 | V29: 52.656991 | W29: TRUE | X29: TRUE | Y29: 4.8794913 | Z29: 4.367446 | AA29: 996 | AB29: 750 | AC29: 12 | AD29: 12 | AE29: TRUE | AF29: TRUE | AG29: 2.053658 | AH29: 2.7272578 | AI29: 619 | AJ29: 394 | AK29: 6 | AL29: 6 | AM29: -5.2884615 | AN29: 161.18143
A30: 2 | B30: 2011 | C30: 3363.68 | D30: 363607 | E30: 4641.5 | F30: 3774.7551 | G30: 4 | H30: 4 | I30: 0.72469676 | J30: -1.9746568 | K30: 7.7561006 | L30: 0.89109886 | M30: -0.91538267 | N30: 6.6041231 | O30: 5.6282875 | P30: 2411 | Q30: 4 | R30: 2206 | S30: 4 | T30: 114805.1 | U30: 4 | V30: 52.042203 | W30: TRUE | X30: TRUE | Y30: 6.6307854 | Z30: 6.0669899 | AA30: 865 | AB30: 1261 | AC30: 12 | AD30: 12 | AE30: TRUE | AF30: TRUE | AG30: 3.46803 | AH30: 2.3789421 | AI30: 171 | AJ30: 421 | AK30: 6 | AL30: 6 | AM30: 6.8527919 | AN30: -72.374798
A31: 2 | B31: 2012 | C31: 3468.51 | D31: 362286 | E31: 4580.75 | F31: 3560.59 | G31: 4 | H31: 4 | I31: 0.7571926 | J31: -1.3088441 | K31: 4.4840606 | L31: 0.97413911 | M31: -5.6736162 | N31: 9.3188597 | O31: 3.1165271 | P31: 2961 | Q31: 4 | R31: 2479 | S31: 4 | T31: 127027.2 | U31: 4 | V31: 51.241307 | W31: TRUE | X31: TRUE | Y31: 8.1731008 | Z31: 6.8426602 | AA31: 1023 | AB31: 837 | AC31: 12 | AD31: 12 | AE31: TRUE | AF31: TRUE | AG31: 2.3103294 | AH31: 2.8237359 | AI31: 468 | AJ31: 561 | AK31: 6 | AL31: 6 | AM31: 33.254157 | AN31: 173.68421
A32: 2 | B32: 2013 | C32: 3589.06 | D32: 360289 | E32: 4773.5 | F32: 3484.0622 | G32: 4 | H32: 4 | I32: 0.75187179 | J32: 4.2078262 | K32: -0.70270197 | L32: 1.0301366 | M32: -2.1493014 | N32: 5.7484078 | O32: 3.4755558 | P32: 3120 | Q32: 4 | R32: 2716 | S32: 4 | T32: 142034.7 | U32: 4 | V32: 52.295545 | W32: TRUE | X32: TRUE | Y32: 8.6597148 | Z32: 7.5383928 | AA32: 1044 | AB32: 1204 | AC32: 12 | AD32: 12 | AE32: TRUE | AF32: TRUE | AG32: 3.3417618 | AH32: 2.8976738 | AI32: 589 | AJ32: 536 | AK32: 6 | AL32: 6 | AM32: -4.456328 | AN32: 25.854701
A33: 2 | B33: 2014 | C33: 3677.79 | D33: 358614 | E33: 4706 | F33: 3454.4787 | G33: 4 | H33: 4 | I33: 0.78151084 | J33: -1.4140568 | K33: 3.9420344 | L33: 1.064644 | M33: -0.84911042 | N33: 3.3497889 | O33: 2.4722351 | P33: 2683 | Q33: 4 | R33: 2498 | S33: 4 | T33: 130089.4 | U33: 4 | V33: 52.077422 | W33: TRUE | X33: TRUE | Y33: 7.4815819 | Z33: 6.9657069 | AA33: 1225 | AB33: 1208 | AC33: 12 | AD33: 12 | AE33: TRUE | AF33: TRUE | AG33: 3.3685244 | AH33: 3.4159291 | AI33: 554 | AJ33: 591 | AK33: 6 | AL33: 6 | AM33: 10.261194 | AN33: -5.942275
A34: 2 | B34: 2015 | C34: 3850.09 | D34: 356961 | E34: 4725.75 | F34: 3565.0809 | G34: 4 | H34: 4 | I34: 0.81470454 | J34: 0.41967701 | K34: 4.2473764 | L34: 1.0799446 | M34: 3.2017051 | N34: 1.43716 | O34: 4.6848787 | P34: 2746 | Q34: 4 | R34: 2677 | S34: 4 | T34: 138906.4 | U34: 4 | V34: 51.888831 | W34: TRUE | X34: TRUE | Y34: 7.6927171 | Z34: 7.4994187 | AA34: 940 | AB34: 1129 | AC34: 12 | AD34: 12 | AE34: TRUE | AF34: TRUE | AG34: 3.1628105 | AH34: 2.6333409 | AI34: 217 | AJ34: 488 | AK34: 6 | AL34: 6 | AM34: -17.428088 | AN34: -60.830325
A35: 2 | B35: 2016 | C35: 3950.95 | D35: 354990 | E35: 4867.75 | F35: 3708.8685 | G35: 4 | H35: 4 | I35: 0.81165836 | J35: 3.0048141 | K35: -0.37390003 | L35: 1.065271 | M35: 4.0332228 | N35: -1.3587427 | O35: 2.619679 | P35: 2653 | Q35: 4 | R35: 2624 | S35: 4 | T35: 140142.1 | U35: 4 | V35: 53.407813 | W35: TRUE | X35: TRUE | Y35: 7.47345 | Z35: 7.3917575 | AA35: 864 | AB35: 1261 | AC35: 12 | AD35: 12 | AE35: TRUE | AF35: TRUE | AG35: 3.5522127 | AH35: 2.4338714 | AI35: 474 | AJ35: 776 | AK35: 6 | AL35: 6 | AM35: 59.016393 | AN35: 118.43318
A36: 2 | B36: 2017 | C36: 4185.1 | D36: 353215 | E36: 5105.75 | F36: 3921.6367 | G36: 4 | H36: 4 | I36: 0.81968369 | J36: 4.8893226 | K36: 0.98875667 | L36: 1.067182 | M36: 5.736741 | N36: 0.17939054 | O36: 5.9264228 | P36: 3073 | Q36: 4 | R36: 3075 | S36: 4 | T36: 158387.8 | U36: 4 | V36: 51.508228 | W36: TRUE | X36: TRUE | Y36: 8.7000835 | Z36: 8.7057458 | AA36: 1432 | AB36: 2087 | AC36: 12 | AD36: 12 | AE36: TRUE | AF36: TRUE | AG36: 5.9085826 | AH36: 4.054188 | AI36: 714 | AJ36: 880 | AK36: 6 | AL36: 6 | AM36: 13.402062 | AN36: 50.632911
A37: 2 | B37: 2018 | C37: 4481.39 | D37: 351254 | E37: 5465 | F37: 4336.2128 | G37: 4 | H37: 4 | I37: 0.82001647 | J37: 7.0361847 | K37: 0.040598402 | L37: 1.0334802 | M37: 10.571505 | N37: -3.1580157 | O37: 7.0796397 | P37: 3517 | Q37: 4 | R37: 3484 | S37: 4 | T37: 178593.3 | U37: 4 | V37: 51.260993 | W37: TRUE | X37: TRUE | Y37: 10.012697 | Z37: 9.9187483 | AA37: 1139 | AB37: 1929 | AC37: 12 | AD37: 12 | AE37: TRUE | AF37: TRUE | AG37: 5.4917524 | AH37: 3.2426677 | AI37: 589 | AJ37: 1095 | AK37: 6 | AL37: 6 | AM37: 24.431818 | AN37: -17.507003
A38: 2 | B38: 2019 | C38: 4957.38 | D38: 349021 | E38: 6092 | F38: 4921.522 | G38: 4 | H38: 4 | I38: 0.81375246 | J38: 11.47301 | K38: -0.76388785 | L38: 1.007286 | M38: 13.498168 | N38: -2.5345663 | O38: 10.621481 | P38: 3210 | Q38: 4 | R38: 3251 | S38: 4 | T38: 166697.2 | U38: 4 | V38: 51.275669 | W38: TRUE | X38: TRUE | Y38: 9.1971543 | Z38: 9.3146258 | AA38: 1340 | AB38: 2089 | AC38: 12 | AD38: 12 | AE38: TRUE | AF38: TRUE | AG38: 5.9853132 | AH38: 3.8393105 | AI38: 783 | AJ38: 971 | AK38: 6 | AL38: 6 | AM38: -11.324201 | AN38: 32.937182
A39: 2 | B39: 2020 | C39: 5252.17 | D39: 341716 | E39: 6471.2202 | F39: 5453.7588 | G39: 4 | H39: 4 | I39: 0.81161974 | J39: 6.2248879 | K39: -0.26208549 | L39: 0.96303673 | M39: 10.814475 | N39: -4.3929163 | O39: 5.9464879 | P39: 2806 | Q39: 4 | R39: 2845 | S39: 4 | T39: 145169.8 | U39: 4 | V39: 51.026292 | W39: TRUE | X39: TRUE | Y39: 8.2114973 | Z39: 8.3256271 | AA39: 1665 | AB39: 2622 | AC39: 12 | AD39: 12 | AE39: TRUE | AF39: TRUE | AG39: 7.6730384 | AH39: 4.8724672 | AI39: 873 | AJ39: 1201 | AK39: 6 | AL39: 6 | AM39: 23.686921 | AN39: 11.494253
A40: 2 | B40: 2021 | C40: 5848.22 | D40: 336665 | E40: 7214.7259 | F40: 5947 | G40: 4 | H40: 4 | I40: 0.8105949 | J40: 11.48942 | K40: -0.12627005 | L40: 0.98338994 | M40: 9.04406 | N40: 2.1134417 | O40: 11.348643 | P40: 3658 | Q40: 4 | R40: 3729 | S40: 4 | T40: 189103 | U40: 4 | V40: 50.711451 | W40: TRUE | X40: TRUE | Y40: 10.8654 | Z40: 11.076292 | AA40: 1438 | AB40: 2263 | AC40: 12 | AD40: 12 | AE40: TRUE | AF40: TRUE | AG40: 6.7218155 | AH40: 4.2713083 | AI40: 901 | AJ40: 1398 | AK40: 6 | AL40: 6 | AM40: 16.402998 | AN40: 3.207331
A41: 2 | B41: 2022 | C41: 6435.59 | D41: 331898 | E41: 7945.8095 | F41: 6537.25 | G41: 4 | H41: 4 | I41: 0.8099351 | J41: 10.133214 | K41: -0.081397009 | L41: 0.98444912 | M41: 9.9251724 | N41: 0.10770641 | O41: 10.043569 | P41: 3411 | Q41: 4 | R41: 3492 | S41: 4 | T41: 169541.4 | U41: 4 | V41: 48.551375 | W41: TRUE | X41: TRUE | Y41: 10.277254 | Z41: 10.521305 | AA41: 1642 | AB41: 1522 | AC41: 12 | AD41: 12 | AE41: TRUE | AF41: TRUE | AG41: 4.5857462 | AH41: 4.9473031 | AI41: 561 | AJ41: 395 | AK41: 6 | AL41: 6 | AM41: -71.745351 | AN41: -37.735849
A42: 2 | B42: 2023 | C42: 7478.19 | D42: 328370 | E42: 8622.3034 | F42: 7005.5 | G42: 4 | H42: 4 | I42: 0.86730769 | J42: 8.5138454 | K42: 7.0836024 | L42: 1.0674741 | M42: 7.1627978 | N42: 8.4336516 | O42: 16.200535 | Q42: 2 | R42: 3857 | S42: 4 | T42: 190597.1 | U42: 4 | V42: 49.415893 | W42: FALSE | X42: TRUE | Z42: 11.745896 | AA42: 2375 | AB42: 1327 | AC42: 12 | AD42: 12 | AE42: TRUE | AF42: TRUE | AG42: 4.0411731 | AH42: 7.2326948 | AI42: 1102 | AJ42: 548 | AK42: 6 | AL42: 6 | AM42: 38.734177 | AN42: 96.434938
A43: 2 | B43: 2024 | C43: 8448.23 | D43: 324984 | E43: 9137.6731 | F43: 7759.5 | G43: 4 | H43: 4 | I43: 0.92454938 | J43: 5.9771701 | K43: 6.599929 | L43: 1.0887596 | M43: 10.762972 | N43: 1.9940022 | O43: 12.971588 | Q43: 2 | R43: 4328 | S43: 4 | T43: 213897.8 | U43: 4 | V43: 49.421858 | W43: FALSE | X43: TRUE | Z43: 13.317579 | AA43: 1513 | AB43: 1828 | AC43: 12 | AD43: 12 | AE43: TRUE | AF43: TRUE | AG43: 5.6248923 | AH43: 4.6556138 | AI43: 815 | AJ43: 993 | AK43: 6 | AL43: 6 | AM43: 81.20438 | AN43: -26.043557
A44: 2 | B44: 2025 | C44: 9219.1 | D44: 322464 | E44: 9950.4314 | F44: 7782.5 | G44: 4 | H44: 4 | I44: 0.92650254 | J44: 8.8945869 | K44: 0.21125594 | L44: 1.1845936 | M44: 0.29641085 | N44: 8.8021319 | O44: 9.1246332 | AA44: 1178 | AB44: 1756 | AC44: 12 | AD44: 12 | AE44: TRUE | AF44: TRUE | AG44: 5.4455691 | AH44: 3.653121 | AI44: 345 | AJ44: 444 | AK44: 6 | AL44: 6 | AM44: -55.287009 | AN44: -57.668712
A45: 2 | B45: 2026 | AI45: 985 | AJ45: 539 | AK45: 6 | AL45: 6 | AM45: 21.396396 | AN45: 185.50725
A46: 3 | B46: 2005 | C46: 3017.45 | D46: 458807 | AA46: 2636 | AB46: 3299 | AC46: 12 | AD46: 12 | AE46: TRUE | AF46: TRUE | AG46: 7.1903872 | AH46: 5.7453352 | AI46: 1263 | AJ46: 1373 | AK46: 6 | AL46: 6
A47: 3 | B47: 2006 | C47: 3177.7 | D47: 457630 | AA47: 3099 | AB47: 6065 | AC47: 12 | AD47: 12 | AE47: TRUE | AF47: TRUE | AG47: 13.253065 | AH47: 6.7718463 | AI47: 1118 | AJ47: 3072 | AK47: 6 | AL47: 6 | AM47: 123.74363 | AN47: -11.480602
A48: 3 | B48: 2007 | C48: 3473.08 | D48: 456103 | E48: 6590.25 | F48: 5485.1153 | G48: 4 | H48: 4 | I48: 0.52700277 | L48: 0.63318268 | AA48: 3295 | AB48: 5857 | AC48: 12 | AD48: 12 | AE48: TRUE | AF48: TRUE | AG48: 12.841398 | AH48: 7.2242454 | AI48: 1021 | AJ48: 3352 | AK48: 6 | AL48: 6 | AM48: 9.1145833 | AN48: -8.6762075
A49: 3 | B49: 2008 | C49: 3847.9 | D49: 455717 | E49: 6862 | F49: 5949.3762 | G49: 4 | H49: 4 | I49: 0.56075488 | J49: 4.1235158 | K49: 6.4045418 | L49: 0.64677369 | M49: 8.4640137 | N49: 2.1464596 | O49: 10.79215 | AA49: 4550 | AB49: 5740 | AC49: 12 | AD49: 12 | AE49: TRUE | AF49: TRUE | AG49: 12.595536 | AH49: 9.9842666 | AI49: 1772 | AJ49: 2867 | AK49: 6 | AL49: 6 | AM49: -14.468974 | AN49: 73.555338
A50: 3 | B50: 2009 | C50: 4053.17 | D50: 455830 | E50: 5624 | F50: 5520.716 | G50: 4 | H50: 4 | I50: 0.72069168 | J50: -18.041387 | K50: 28.521695 | L50: 0.7341747 | M50: -7.2051297 | N50: 13.513385 | O50: 5.3345981 | AA50: 4276 | AB50: 4092 | AC50: 12 | AD50: 12 | AE50: TRUE | AF50: TRUE | AG50: 8.9770309 | AH50: 9.3806902 | AI50: 1523 | AJ50: 2023 | AK50: 6 | AL50: 6 | AM50: -29.438437 | AN50: -14.051919
A51: 3 | B51: 2010 | C51: 4108.37 | D51: 460416 | E51: 5501.2663 | F51: 5516.9316 | G51: 4 | H51: 4 | I51: 0.74680442 | J51: -2.1823203 | K51: 3.6232891 | L51: 0.74468388 | M51: -0.068548707 | N51: 1.4314269 | O51: 1.361897 | P51: 3120 | Q51: 4 | R51: 1359 | S51: 4 | T51: 76682.3 | U51: 4 | V51: 56.425533 | W51: TRUE | X51: TRUE | Y51: 6.7764804 | Z51: 2.9516785 | AA51: 3534 | AB51: 4688 | AC51: 12 | AD51: 12 | AE51: TRUE | AF51: TRUE | AG51: 10.182096 | AH51: 7.6756672 | AI51: 1611 | AJ51: 2652 | AK51: 6 | AL51: 6 | AM51: 31.092437 | AN51: 5.7780696
A52: 3 | B52: 2011 | C52: 4327.35 | D52: 460435 | E52: 5584.5 | F52: 5446.6027 | G52: 4 | H52: 4 | I52: 0.77488584 | J52: 1.5129915 | K52: 3.7602112 | L52: 0.79450443 | M52: -1.2747823 | N52: 6.6901617 | O52: 5.3300944 | P52: 5696 | Q52: 4 | R52: 3758 | S52: 4 | T52: 208731.3 | U52: 4 | V52: 55.543188 | W52: TRUE | X52: TRUE | Y52: 12.37091 | Z52: 8.1618469 | AA52: 4422 | AB52: 4595 | AC52: 12 | AD52: 12 | AE52: TRUE | AF52: TRUE | AG52: 9.9796931 | AH52: 9.6039615 | AI52: 1009 | AJ52: 1711 | AK52: 6 | AL52: 6 | AM52: -35.482655 | AN52: -37.368094
A53: 3 | B53: 2012 | C53: 4411.71 | D53: 460354 | E53: 5522.2079 | F53: 5143.7552 | G53: 4 | H53: 4 | I53: 0.79890328 | J53: -1.1154464 | K53: 3.0994804 | L53: 0.85768273 | M53: -5.560301 | N53: 7.9519123 | O53: 1.949461 | P53: 6663 | Q53: 4 | R53: 4770 | S53: 4 | T53: 266944.4 | U53: 4 | V53: 55.963187 | W53: TRUE | X53: TRUE | Y53: 14.473644 | Z53: 10.361591 | AA53: 5095 | AB53: 3856 | AC53: 12 | AD53: 12 | AE53: TRUE | AF53: TRUE | AG53: 8.3761627 | AH53: 11.06757 | AI53: 1144 | AJ53: 1715 | AK53: 6 | AL53: 6 | AM53: 0.23378141 | AN53: 13.379584
A54: 3 | B54: 2013 | C54: 4562.66 | D54: 460815 | E54: 5730.8026 | F54: 4837.47 | G54: 4 | H54: 4 | I54: 0.79616422 | J54: 3.7773791 | K54: -0.34285248 | L54: 0.94319137 | M54: -5.9545055 | N54: 9.9697293 | O54: 3.4215758 | P54: 7041 | Q54: 4 | R54: 6271 | S54: 4 | T54: 341825.5 | U54: 4 | V54: 54.50893 | W54: TRUE | X54: TRUE | Y54: 15.279451 | Z54: 13.608498 | AA54: 3851 | AB54: 4509 | AC54: 12 | AD54: 12 | AE54: TRUE | AF54: TRUE | AG54: 9.7848377 | AH54: 8.3569328 | AI54: 1645 | AJ54: 2018 | AK54: 6 | AL54: 6 | AM54: 17.667638 | AN54: 43.793706
A55: 3 | B55: 2014 | C55: 4814.14 | D55: 461935 | E55: 5767.0818 | F55: 4935.5658 | G55: 4 | H55: 4 | I55: 0.83476187 | J55: 0.63305646 | K55: 4.8479504 | L55: 0.97539779 | M55: 2.0278324 | N55: 3.4146219 | O55: 5.5116971 | P55: 5969 | Q55: 4 | R55: 5469 | S55: 4 | T55: 301175.5 | U55: 4 | V55: 55.069574 | W55: TRUE | X55: TRUE | Y55: 12.921731 | Z55: 11.839328 | AA55: 3945 | AB55: 5057 | AC55: 12 | AD55: 12 | AE55: TRUE | AF55: TRUE | AG55: 10.947428 | AH55: 8.5401626 | AI55: 1275 | AJ55: 2312 | AK55: 6 | AL55: 6 | AM55: 14.56888 | AN55: -22.492401
A56: 3 | B56: 2015 | C56: 4992.14 | D56: 461798 | E56: 5954.9574 | F56: 5105.0122 | G56: 4 | H56: 4 | I56: 0.83831666 | J56: 3.2577231 | K56: 0.42584534 | L56: 0.97788992 | M56: 3.4331713 | N56: 0.25549825 | O56: 3.6974413 | P56: 7167 | Q56: 4 | R56: 6822 | S56: 4 | T56: 362149.7 | U56: 4 | V56: 53.085561 | W56: TRUE | X56: TRUE | Y56: 15.519773 | Z56: 14.772693 | AA56: 4506 | AB56: 6007 | AC56: 12 | AD56: 12 | AE56: TRUE | AF56: TRUE | AG56: 13.007852 | AH56: 9.757513 | AI56: 1205 | AJ56: 3685 | AK56: 6 | AL56: 6 | AM56: 59.385813 | AN56: -5.4901961
A57: 3 | B57: 2016 | C57: 5118.59 | D57: 462996 | E57: 6350.4566 | F57: 5442.2419 | G57: 4 | H57: 4 | I57: 0.80601921 | J57: 6.641512 | K57: -3.8526556 | L57: 0.94052968 | M57: 6.6058532 | N57: -3.820495 | O57: 2.5329818 | P57: 8058 | Q57: 4 | R57: 7704 | S57: 4 | T57: 403973.8 | U57: 4 | V57: 52.43689 | W57: TRUE | X57: TRUE | Y57: 17.404038 | Z57: 16.639453 | AA57: 5080 | AB57: 6461 | AC57: 12 | AD57: 12 | AE57: TRUE | AF57: TRUE | AG57: 13.954764 | AH57: 10.972017 | AI57: 1456 | AJ57: 3182 | AK57: 6 | AL57: 6 | AM57: -13.649932 | AN57: 20.829876
A58: 3 | B58: 2017 | C58: 5312.48 | D58: 464293 | E58: 6644.1927 | F58: 5973.0681 | G58: 4 | H58: 4 | I58: 0.79956742 | J58: 4.6254326 | K58: -0.80045102 | L58: 0.88940556 | M58: 9.7538164 | N58: -5.4356735 | O58: 3.7879572 | P58: 8737 | Q58: 4 | R58: 8573 | S58: 4 | T58: 461718 | U58: 4 | V58: 53.857226 | W58: TRUE | X58: TRUE | Y58: 18.817859 | Z58: 18.464633 | AA58: 6442 | AB58: 8002 | AC58: 12 | AD58: 12 | AE58: TRUE | AF58: TRUE | AG58: 17.234806 | AH58: 13.874859 | AI58: 2460 | AJ58: 4658 | AK58: 6 | AL58: 6 | AM58: 46.385921 | AN58: 68.956044
A59: 3 | B59: 2018 | C59: 5642 | D59: 464829 | E59: 7492.4303 | F59: 6861.047 | G59: 4 | H59: 4 | I59: 0.75302669 | J59: 12.766602 | K59: -5.8207384 | L59: 0.82232347 | M59: 14.866378 | N59: -7.5423508 | O59: 6.2027528 | P59: 9892 | Q59: 4 | R59: 9682 | S59: 4 | T59: 508849.1 | U59: 4 | V59: 52.556197 | W59: TRUE | X59: TRUE | Y59: 21.280944 | Z59: 20.829165 | AA59: 6851 | AB59: 5904 | AC59: 12 | AD59: 12 | AE59: TRUE | AF59: TRUE | AG59: 12.701445 | AH59: 14.738753 | AI59: 1894 | AJ59: 2721 | AK59: 6 | AL59: 6 | AM59: -41.584371 | AN59: -23.00813
A60: 3 | B60: 2019 | C60: 6154.35 | D60: 468158 | E60: 8417.4643 | F60: 7745.0088 | G60: 4 | H60: 4 | I60: 0.73114061 | J60: 12.346247 | K60: -2.9064144 | L60: 0.79462143 | M60: 12.883774 | N60: -3.3687521 | O60: 9.0809996 | P60: 9958 | Q60: 4 | R60: 9978 | S60: 4 | T60: 519554.1 | U60: 4 | V60: 52.069964 | W60: TRUE | X60: TRUE | Y60: 21.270597 | Z60: 21.313317 | AA60: 7265 | AB60: 7256 | AC60: 12 | AD60: 12 | AE60: TRUE | AF60: TRUE | AG60: 15.499041 | AH60: 15.518265 | AI60: 2914 | AJ60: 3103 | AK60: 6 | AL60: 6 | AM60: 14.038956 | AN60: 53.854277
A61: 3 | B61: 2020 | C61: 6490.53 | D61: 487262 | E61: 8992.9852 | F61: 8564.1032 | G61: 4 | H61: 4 | I61: 0.72173254 | J61: 6.8372241 | K61: -1.2867672 | L61: 0.7578762 | M61: 10.57577 | N61: -4.6242432 | O61: 5.4624778 | P61: 8406 | Q61: 4 | R61: 8475 | S61: 4 | T61: 444639.9 | U61: 4 | V61: 52.464885 | W61: TRUE | X61: TRUE | Y61: 17.251499 | Z61: 17.393107 | AA61: 6558 | AB61: 7143 | AC61: 12 | AD61: 12 | AE61: TRUE | AF61: TRUE | AG61: 14.659465 | AH61: 13.458878 | AI61: 2459 | AJ61: 2277 | AK61: 6 | AL61: 6 | AM61: -26.619401 | AN61: -15.614276
A62: 3 | B62: 2021 | C62: 7084.42 | D62: 486283 | E62: 10256.825 | F62: 9478.9141 | G62: 4 | H62: 4 | I62: 0.69070305 | J62: 14.053613 | K62: -4.2993051 | L62: 0.7473873 | M62: 10.681923 | N62: -1.3839867 | O62: 9.1501002 | P62: 9593 | Q62: 4 | R62: 9699 | S62: 4 | T62: 523440.4 | U62: 4 | V62: 53.968492 | W62: TRUE | X62: TRUE | Y62: 19.727196 | Z62: 19.945176 | AA62: 7328 | AB62: 6775 | AC62: 12 | AD62: 12 | AE62: TRUE | AF62: TRUE | AG62: 13.932216 | AH62: 15.069414 | AI62: 2458 | AJ62: 3777 | AK62: 6 | AL62: 6 | AM62: 65.876153 | AN62: -0.040666938
A63: 3 | B63: 2022 | C63: 7876.68 | D63: 486226 | E63: 11152.086 | F63: 10566.276 | G63: 4 | H63: 4 | I63: 0.70629653 | J63: 8.7284516 | K63: 2.2576242 | L63: 0.74545469 | M63: 11.471376 | N63: -0.25858142 | O63: 11.183131 | P63: 9129 | Q63: 4 | R63: 9186 | S63: 4 | T63: 482400.1 | U63: 4 | V63: 52.514707 | W63: TRUE | X63: TRUE | Y63: 18.77522 | Z63: 18.892449 | AA63: 7165 | AB63: 5663 | AC63: 12 | AD63: 12 | AE63: TRUE | AF63: TRUE | AG63: 11.646847 | AH63: 14.735946 | AI63: 2152 | AJ63: 3289 | AK63: 6 | AL63: 6 | AM63: -12.920307 | AN63: -12.449146
A64: 3 | B64: 2023 | C64: 8915.97 | D64: 486492 | E64: 11625.297 | F64: 11062.739 | G64: 4 | H64: 4 | I64: 0.76694555 | J64: 4.2432483 | K64: 8.5869064 | L64: 0.80594597 | M64: 4.6985629 | N64: 8.1146822 | O64: 13.194519 | Q64: 1 | S64: 2 | U64: 2 | W64: FALSE | X64: FALSE | AA64: 6236 | AB64: 4664 | AC64: 12 | AD64: 12 | AE64: TRUE | AF64: TRUE | AG64: 9.5870025 | AH64: 12.818299 | AI64: 2291 | AJ64: 1954 | AK64: 6 | AL64: 6 | AM64: -40.589845 | AN64: 6.4591078
A65: 3 | B65: 2024 | C65: 10107.32 | D65: 487834 | E65: 12845.37 | F65: 12681.258 | G65: 4 | H65: 4 | I65: 0.7868454 | J65: 10.494978 | K65: 2.5946888 | L65: 0.79702819 | M65: 14.630362 | N65: -1.1064991 | O65: 13.361979 | P65: 9985 | Q65: 4 | R65: 10037 | S65: 4 | T65: 536100 | U65: 4 | V65: 53.412374 | W65: TRUE | X65: TRUE | Y65: 20.468028 | Z65: 20.574622 | AA65: 6452 | AB65: 5525 | AC65: 12 | AD65: 12 | AE65: TRUE | AF65: TRUE | AG65: 11.325574 | AH65: 13.22581 | AI65: 3364 | AJ65: 3864 | AK65: 6 | AL65: 6 | AM65: 97.748209 | AN65: 46.835443
A66: 3 | B66: 2025 | C66: 10972.26 | D66: 489160 | E66: 14142.416 | F66: 13363.95 | G66: 4 | H66: 4 | I66: 0.77584054 | J66: 10.097388 | K66: -1.3986052 | L66: 0.82103419 | M66: 5.3834739 | N66: 3.0119394 | O66: 8.5575603 | AA66: 5750 | AB66: 5337 | AC66: 12 | AD66: 12 | AE66: TRUE | AF66: TRUE | AG66: 10.910541 | AH66: 11.754845 | AI66: 2194 | AJ66: 3776 | AK66: 6 | AL66: 6 | AM66: -2.2774327 | AN66: -34.780024
A67: 3 | B67: 2026 | AI67: 1618 | AJ67: 3109 | AK67: 6 | AL67: 6 | AM67: -17.664195 | AN67: -26.253418
A68: 4 | B68: 2005 | C68: 2741.05 | D68: 253092 | AA68: 1300 | AC68: 12 | AD68: 0 | AE68: FALSE | AF68: TRUE | AH68: 5.1364721 | AI68: 368 | AK68: 6 | AL68: 0
A69: 4 | B69: 2006 | C69: 2914.02 | D69: 252443 | AA69: 1448 | AB69: 1487 | AC69: 12 | AD69: 12 | AE69: TRUE | AF69: TRUE | AG69: 5.8904386 | AH69: 5.7359483 | AI69: 755 | AJ69: 481 | AK69: 6 | AL69: 6 | AN69: 105.16304
A70: 4 | B70: 2007 | C70: 3198.33 | D70: 251183 | E70: 6880.5 | F70: 5573.8316 | G70: 4 | H70: 4 | I70: 0.46483976 | L70: 0.57381173 | AA70: 1256 | AB70: 1758 | AC70: 12 | AD70: 12 | AE70: TRUE | AF70: TRUE | AG70: 6.9988813 | AH70: 5.0003384 | AI70: 735 | AJ70: 877 | AK70: 6 | AL70: 6 | AM70: 82.328482 | AN70: -2.6490066
A71: 4 | B71: 2008 | C71: 3493.85 | D71: 249787 | E71: 6897 | F71: 5906.4613 | G71: 4 | H71: 4 | I71: 0.50657532 | J71: 0.23980815 | K71: 8.9784827 | L71: 0.59153016 | M71: 5.9677013 | N71: 3.0878472 | O71: 9.239822 | AA71: 1747 | AB71: 1192 | AC71: 12 | AD71: 12 | AE71: TRUE | AF71: TRUE | AG71: 4.7720658 | AH71: 6.9939589 | AI71: 627 | AJ71: 815 | AK71: 6 | AL71: 6 | AM71: -7.0695553 | AN71: -14.693878
A72: 4 | B72: 2009 | C72: 3583.9 | D72: 248889 | E72: 5852.5 | F72: 5460.9422 | G72: 4 | H72: 4 | I72: 0.61237078 | J72: -15.144266 | K72: 20.884448 | L72: 0.65627869 | M72: -7.5429096 | N72: 10.945938 | O72: 2.577386 | AA72: 965 | AB72: 859 | AC72: 12 | AD72: 12 | AE72: TRUE | AF72: TRUE | AG72: 3.4513377 | AH72: 3.8772304 | AI72: 377 | AJ72: 370 | AK72: 6 | AL72: 6 | AM72: -54.601227 | AN72: -39.872408
A73: 4 | B73: 2010 | C73: 3662.62 | D73: 249676 | E73: 5462.6274 | F73: 5365.781 | G73: 4 | H73: 4 | I73: 0.67048688 | J73: -6.6616417 | K73: 9.4903443 | L73: 0.68258843 | M73: -1.7425795 | N73: 4.0089281 | O73: 2.1964899 | P73: 2336 | Q73: 4 | R73: 2066 | S73: 4 | T73: 121581.5 | U73: 4 | V73: 58.848742 | W73: TRUE | X73: TRUE | Y73: 9.3561255 | Z73: 8.274724 | AA73: 1119 | AB73: 890 | AC73: 12 | AD73: 12 | AE73: TRUE | AF73: TRUE | AG73: 3.5646197 | AH73: 4.4818084 | AI73: 801 | AJ73: 585 | AK73: 6 | AL73: 6 | AM73: 58.108108 | AN73: 112.46684
A74: 4 | B74: 2011 | C74: 3938.74 | D74: 249081 | E74: 6238.0323 | F74: 5306.3322 | G74: 4 | H74: 4 | I74: 0.63140744 | J74: 14.194724 | K74: -5.8285168 | L74: 0.74227166 | M74: -1.1079246 | N74: 8.7436634 | O74: 7.5388656 | P74: 2401 | Q74: 4 | R74: 2104 | S74: 4 | T74: 122141.1 | U74: 4 | V74: 58.051854 | W74: TRUE | X74: TRUE | Y74: 9.6394346 | Z74: 8.4470514 | AA74: 1100 | AB74: 1035 | AC74: 12 | AD74: 12 | AE74: TRUE | AF74: TRUE | AG74: 4.1552748 | AH74: 4.4162341 | AI74: 388 | AJ74: 537 | AK74: 6 | AL74: 6 | AM74: -8.2051282 | AN74: -51.560549
A75: 4 | B75: 2012 | C75: 4067.07 | D75: 248574 | E75: 6287.787 | F75: 5068.1914 | G75: 4 | H75: 4 | I75: 0.64682058 | J75: 0.79760187 | K75: 2.4410766 | L75: 0.80246969 | M75: -4.4878593 | N75: 8.109972 | O75: 3.2581485 | P75: 2330 | Q75: 4 | R75: 1942 | S75: 4 | T75: 112565.9 | U75: 4 | V75: 57.963903 | W75: TRUE | X75: TRUE | Y75: 9.3734663 | Z75: 7.8125629 | AA75: 1133 | AB75: 1494 | AC75: 12 | AD75: 12 | AE75: TRUE | AF75: TRUE | AG75: 6.0102827 | AH75: 4.5579988 | AI75: 598 | AJ75: 718 | AK75: 6 | AL75: 6 | AM75: 33.705773 | AN75: 54.123711
A76: 4 | B76: 2013 | C76: 4298.33 | D76: 248362 | E76: 6116.1678 | F76: 4840.6897 | G76: 4 | H76: 4 | I76: 0.70278157 | J76: -2.7294059 | K76: 8.6517033 | L76: 0.88795818 | M76: -4.488815 | N76: 10.653174 | O76: 5.6861574 | P76: 2244 | Q76: 4 | R76: 2078 | S76: 4 | T76: 120222.6 | U76: 4 | V76: 57.854957 | W76: TRUE | X76: TRUE | Y76: 9.0351986 | Z76: 8.3668194 | AA76: 1066 | AB76: 736 | AC76: 12 | AD76: 12 | AE76: TRUE | AF76: TRUE | AG76: 2.9634163 | AH76: 4.292122 | AI76: 366 | AJ76: 229 | AK76: 6 | AL76: 6 | AM76: -68.10585 | AN76: -38.795987
A77: 4 | B77: 2014 | C77: 4457.62 | D77: 247792 | E77: 5908.5282 | F77: 4917.0505 | G77: 4 | H77: 4 | I77: 0.7544383 | J77: -3.394929 | K77: 7.3503252 | L77: 0.9065638 | M77: 1.5774776 | N77: 2.095327 | O77: 3.7058579 | P77: 2229 | Q77: 4 | R77: 2108 | S77: 4 | T77: 123114.3 | U77: 4 | V77: 58.403368 | W77: TRUE | X77: TRUE | Y77: 8.9954478 | Z77: 8.507135 | AA77: 932 | AB77: 855 | AC77: 12 | AD77: 12 | AE77: TRUE | AF77: TRUE | AG77: 3.4504746 | AH77: 3.7612191 | AI77: 535 | AJ77: 448 | AK77: 6 | AL77: 6 | AM77: 95.633188 | AN77: 46.174863
A78: 4 | B78: 2015 | C78: 4566.82 | D78: 247672 | E78: 6245.9571 | F78: 4995.1153 | G78: 4 | H78: 4 | I78: 0.73116416 | J78: 5.7108797 | K78: -3.0849634 | L78: 0.91425717 | M78: 1.5876348 | N78: 0.8486298 | O78: 2.4497378 | P78: 2347 | Q78: 4 | R78: 2215 | S78: 4 | T78: 127302.1 | U78: 4 | V78: 57.472731 | W78: TRUE | X78: TRUE | Y78: 9.4762428 | Z78: 8.9432798 | AA78: 1109 | AB78: 1346 | AC78: 12 | AD78: 12 | AE78: TRUE | AF78: TRUE | AG78: 5.4346071 | AH78: 4.4776963 | AI78: 599 | AJ78: 1007 | AK78: 6 | AL78: 6 | AM78: 124.77679 | AN78: 11.962617
A79: 4 | B79: 2016 | C79: 4798.54 | D79: 247329 | E79: 6551.5645 | F79: 5194.2756 | G79: 4 | H79: 4 | I79: 0.73242658 | J79: 4.892883 | K79: 0.17265925 | L79: 0.92381312 | M79: 3.987102 | N79: 1.0452145 | O79: 5.0739902 | P79: 2015 | Q79: 4 | R79: 1933 | S79: 4 | T79: 111810 | U79: 4 | V79: 57.842732 | W79: TRUE | X79: TRUE | Y79: 8.147043 | Z79: 7.8155008 | AA79: 1216 | AB79: 1549 | AC79: 12 | AD79: 12 | AE79: TRUE | AF79: TRUE | AG79: 6.262913 | AH79: 4.9165282 | AI79: 423 | AJ79: 927 | AK79: 6 | AL79: 6 | AM79: -7.9443893 | AN79: -29.382304
A80: 4 | B80: 2017 | C80: 5045.45 | D80: 246643 | E80: 6879.7233 | F80: 5744.3474 | G80: 4 | H80: 4 | I80: 0.73337978 | J80: 5.0088618 | K80: 0.13014291 | L80: 0.87833302 | M80: 10.58996 | N80: -4.9230843 | O80: 5.1455234 | P80: 2914 | Q80: 4 | R80: 2913 | S80: 4 | T80: 172206.4 | U80: 4 | V80: 59.116512 | W80: TRUE | X80: TRUE | Y80: 11.814647 | Z80: 11.810593 | AA80: 1111 | AB80: 2479 | AC80: 12 | AD80: 12 | AE80: TRUE | AF80: TRUE | AG80: 10.050964 | AH80: 4.5044862 | AI80: 528 | AJ80: 1570 | AK80: 6 | AL80: 6 | AM80: 69.363538 | AN80: 24.822695
A81: 4 | B81: 2018 | C81: 5347.46 | D81: 246204 | E81: 7288.2708 | F81: 6386.1907 | G81: 4 | H81: 4 | I81: 0.73370764 | J81: 5.9384293 | K81: 0.044705116 | L81: 0.83734737 | M81: 11.173477 | N81: -4.6662997 | O81: 5.9857892 | P81: 2971 | Q81: 4 | R81: 2978 | S81: 4 | T81: 176787.6 | U81: 4 | V81: 59.36454 | W81: TRUE | X81: TRUE | Y81: 12.067229 | Z81: 12.095661 | AA81: 1521 | AB81: 1827 | AC81: 12 | AD81: 12 | AE81: TRUE | AF81: TRUE | AG81: 7.4206755 | AH81: 6.1778038 | AI81: 454 | AJ81: 1089 | AK81: 6 | AL81: 6 | AM81: -30.636943 | AN81: -14.015152
A82: 4 | B82: 2019 | C82: 5624.49 | D82: 246244 | E82: 8129.814 | F82: 7054.1142 | G82: 4 | H82: 4 | I82: 0.69183502 | J82: 11.54654 | K82: -5.7069899 | L82: 0.7973347 | M82: 10.458872 | N82: -4.7785039 | O82: 5.1805904 | P82: 2839 | Q82: 4 | R82: 2866 | S82: 4 | T82: 170184.6 | U82: 4 | V82: 59.38053 | W82: TRUE | X82: TRUE | Y82: 11.529215 | Z82: 11.638862 | AA82: 1479 | AB82: 1525 | AC82: 12 | AD82: 12 | AE82: TRUE | AF82: TRUE | AG82: 6.1930443 | AH82: 6.0062377 | AI82: 688 | AJ82: 1091 | AK82: 6 | AL82: 6 | AM82: 0.18365473 | AN82: 51.54185
A83: 4 | B83: 2020 | C83: 5848.66 | D83: 246637 | E83: 8149.7051 | F83: 7616.9652 | G83: 4 | H83: 4 | I83: 0.71765296 | J83: 0.24466886 | K83: 3.7318064 | L83: 0.7678465 | M83: 7.9790452 | N83: -3.6983466 | O83: 3.9856058 | P83: 3028 | Q83: 4 | R83: 3053 | S83: 4 | T83: 178171.2 | U83: 4 | V83: 58.359384 | W83: TRUE | X83: TRUE | Y83: 12.277152 | Z83: 12.378516 | AA83: 1985 | AB83: 1533 | AC83: 12 | AD83: 12 | AE83: TRUE | AF83: TRUE | AG83: 6.2156124 | AH83: 8.0482653 | AI83: 829 | AJ83: 587 | AK83: 6 | AL83: 6 | AM83: -46.19615 | AN83: 20.494186
A84: 4 | B84: 2021 | C84: 6298.57 | D84: 244862 | E84: 9703.8733 | F84: 8316.8292 | G84: 4 | H84: 4 | I84: 0.64907793 | J84: 19.070238 | K84: -9.5554583 | L84: 0.75732828 | M84: 9.1882275 | N84: -1.3698329 | O84: 7.6925313 | P84: 3917 | Q84: 4 | R84: 3980 | S84: 4 | T84: 228552.6 | U84: 4 | V84: 57.425276 | W84: TRUE | X84: TRUE | Y84: 15.996766 | Z84: 16.254053 | AA84: 2375 | AB84: 1641 | AC84: 12 | AD84: 12 | AE84: TRUE | AF84: TRUE | AG84: 6.701734 | AH84: 9.6993409 | AI84: 807 | AJ84: 614 | AK84: 6 | AL84: 6 | AM84: 4.5996593 | AN84: -2.6537998
A85: 4 | B85: 2022 | C85: 6985.73 | D85: 243770 | E85: 10280.432 | F85: 9314.9209 | G85: 4 | H85: 4 | I85: 0.67951715 | J85: 5.9415341 | K85: 4.6896091 | L85: 0.74995055 | M85: 12.000867 | N85: -0.97417942 | O85: 10.909778 | P85: 3391 | Q85: 4 | R85: 3456 | S85: 4 | T85: 195229.3 | U85: 4 | V85: 56.489959 | W85: TRUE | X85: TRUE | Y85: 13.910653 | Z85: 14.177298 | AA85: 1001 | AB85: 1499 | AC85: 12 | AD85: 12 | AE85: TRUE | AF85: TRUE | AG85: 6.149239 | AH85: 4.1063297 | AI85: 678 | AJ85: 1148 | AK85: 6 | AL85: 6 | AM85: 86.970684 | AN85: -15.98513
A86: 4 | B86: 2023 | C86: 7890.4 | D86: 242141 | E86: 10975.377 | F86: 9856.4739 | G86: 4 | H86: 4 | I86: 0.71891833 | J86: 6.7598828 | K86: 5.7984088 | L86: 0.80052969 | M86: 5.8138227 | N86: 6.7443311 | O86: 12.950257 | Q86: 1 | S86: 2 | U86: 2 | W86: FALSE | X86: FALSE | AA86: 1374 | AB86: 788 | AC86: 12 | AD86: 12 | AE86: TRUE | AF86: TRUE | AG86: 3.2543022 | AH86: 5.6743798 | AI86: 844 | AJ86: 328 | AK86: 6 | AL86: 6 | AM86: -71.428571 | AN86: 24.483776
A87: 4 | B87: 2024 | C87: 8999.18 | D87: 240554 | E87: 12746.783 | F87: 11406.117 | G87: 4 | H87: 4 | I87: 0.70599615 | J87: 16.13982 | K87: -1.7974486 | L87: 0.78897843 | M87: 15.722081 | N87: -1.4429525 | O87: 14.052266 | Q87: 1 | R87: 2676 | S87: 4 | T87: 149035 | U87: 4 | V87: 55.693199 | W87: FALSE | X87: TRUE | Z87: 11.124321 | AA87: 1813 | AB87: 1816 | AC87: 12 | AD87: 12 | AE87: TRUE | AF87: TRUE | AG87: 7.5492405 | AH87: 7.5367693 | AI87: 479 | AJ87: 814 | AK87: 6 | AL87: 6 | AM87: 148.17073 | AN87: -43.246445
A88: 4 | B88: 2025 | C88: 9795.07 | D88: 239325 | E88: 13246.877 | F88: 11784.179 | G88: 4 | H88: 4 | I88: 0.73942486 | J88: 3.9232901 | K88: 4.7349712 | L88: 0.83120516 | M88: 3.3145545 | N88: 5.3520761 | O88: 8.844028 | AA88: 864 | AB88: 1786 | AC88: 12 | AD88: 12 | AE88: TRUE | AF88: TRUE | AG88: 7.4626554 | AH88: 3.6101536 | AI88: 296 | AJ88: 322 | AK88: 6 | AL88: 6 | AM88: -60.44226 | AN88: -38.204593
A89: 4 | B89: 2026 | AI89: 247 | AJ89: 1533 | AK89: 6 | AL89: 6 | AM89: 376.08696 | AN89: -16.554054
A90: 5 | B90: 2005 | C90: 3395.63 | D90: 318744 | AA90: 317 | AB90: 320 | AC90: 12 | AD90: 12 | AE90: TRUE | AF90: TRUE | AG90: 1.0039405 | AH90: 0.99452852 | AI90: 92 | AJ90: 92 | AK90: 6 | AL90: 6
A91: 5 | B91: 2006 | C91: 3523.92 | D91: 315996 | AA91: 440 | AB91: 416 | AC91: 12 | AD91: 12 | AE91: TRUE | AF91: TRUE | AG91: 1.3164724 | AH91: 1.3924227 | AI91: 98 | AJ91: 137 | AK91: 6 | AL91: 6 | AM91: 48.913043 | AN91: 6.5217391
A92: 5 | B92: 2007 | C92: 3727.38 | D92: 313461 | E92: 5078.6225 | F92: 3201.2285 | G92: 4 | H92: 4 | I92: 0.73393524 | L92: 1.1643592 | AA92: 619 | AB92: 769 | AC92: 12 | AD92: 12 | AE92: TRUE | AF92: TRUE | AG92: 2.4532557 | AH92: 1.9747273 | AI92: 160 | AJ92: 328 | AK92: 6 | AL92: 6 | AM92: 139.41606 | AN92: 63.265306
A93: 5 | B93: 2008 | C93: 4150.44 | D93: 311179 | E93: 5457.5525 | F93: 3713.4797 | G93: 4 | H93: 4 | I93: 0.76049475 | J93: 7.4612752 | K93: 3.6187812 | L93: 1.1176687 | M93: 16.001707 | N93: -4.0099783 | O93: 11.350064 | AA93: 1303 | AB93: 658 | AC93: 12 | AD93: 12 | AE93: TRUE | AF93: TRUE | AG93: 2.1145386 | AH93: 4.1873006 | AI93: 378 | AJ93: 449 | AK93: 6 | AL93: 6 | AM93: 36.890244 | AN93: 136.25
A94: 5 | B94: 2009 | C94: 4494.03 | D94: 308724 | E94: 4948.9425 | F94: 3477.5618 | G94: 4 | H94: 4 | I94: 0.90807885 | J94: -9.319379 | K94: 19.406328 | L94: 1.2922933 | M94: -6.3530138 | N94: 15.624009 | O94: 8.2783994 | AA94: 949 | AB94: 920 | AC94: 12 | AD94: 12 | AE94: TRUE | AF94: TRUE | AG94: 2.980008 | AH94: 3.0739431 | AI94: 423 | AJ94: 395 | AK94: 6 | AL94: 6 | AM94: -12.026726 | AN94: 11.904762
A95: 5 | B95: 2010 | C95: 4563.66 | D95: 312294 | E95: 4949.75 | F95: 3578.837 | G95: 4 | H95: 4 | I95: 0.92199808 | J95: 0.016316617 | K95: 1.5328221 | L95: 1.2751796 | M95: 2.9122454 | N95: -1.32429 | O95: 1.5493889 | P95: 673 | Q95: 4 | R95: 682 | S95: 4 | T95: 37327.4 | U95: 4 | V95: 54.732258 | W95: TRUE | X95: TRUE | Y95: 2.1550206 | Z95: 2.1838396 | AA95: 1137 | AB95: 1670 | AC95: 12 | AD95: 12 | AE95: TRUE | AF95: TRUE | AG95: 5.3475251 | AH95: 3.6408 | AI95: 333 | AJ95: 250 | AK95: 6 | AL95: 6 | AM95: -36.708861 | AN95: -21.276596
A96: 5 | B96: 2011 | C96: 5013.92 | D96: 310434 | E96: 4761.6499 | F96: 3486.0745 | G96: 4 | H96: 4 | I96: 1.0529796 | J96: -3.8001936 | K96: 14.206263 | L96: 1.4382711 | M96: -2.591973 | N96: 12.789682 | O96: 9.8662039 | P96: 949 | Q96: 4 | R96: 971 | S96: 4 | T96: 54200.6 | U96: 4 | V96: 55.819361 | W96: TRUE | X96: TRUE | Y96: 3.0570105 | Z96: 3.127879 | AA96: 663 | AB96: 1290 | AC96: 12 | AD96: 12 | AE96: TRUE | AF96: TRUE | AG96: 4.1554727 | AH96: 2.1357197 | AI96: 147 | AJ96: 270 | AK96: 6 | AL96: 6 | AM96: 8 | AN96: -55.855856
A97: 5 | B97: 2012 | C97: 4966.8 | D97: 308269 | E97: 4952.7126 | F97: 3369.118 | G97: 4 | H97: 4 | I97: 1.0028444 | J97: 4.0125317 | K97: -4.761268 | L97: 1.4742137 | M97: -3.3549609 | N97: 2.4990183 | O97: -0.93978364 | P97: 904 | Q97: 4 | R97: 908 | S97: 4 | T97: 48997.7 | U97: 4 | V97: 53.962225 | W97: TRUE | X97: TRUE | Y97: 2.9325038 | Z97: 2.9454794 | AA97: 376 | AB97: 606 | AC97: 12 | AD97: 12 | AE97: TRUE | AF97: TRUE | AG97: 1.9658156 | AH97: 1.219714 | AI97: 221 | AJ97: 333 | AK97: 6 | AL97: 6 | AM97: 23.333333 | AN97: 50.340136
A98: 5 | B98: 2013 | C98: 5270.37 | D98: 305995 | E98: 4883.8429 | F98: 3270.8292 | G98: 4 | H98: 4 | I98: 1.0791441 | J98: -1.3905465 | K98: 7.6083274 | L98: 1.6113253 | M98: -2.9173456 | N98: 9.3006616 | O98: 6.1119836 | P98: 983 | Q98: 4 | R98: 996 | S98: 4 | T98: 54623.8 | U98: 4 | V98: 54.843173 | W98: TRUE | X98: TRUE | Y98: 3.2124708 | Z98: 3.2549551 | AA98: 510 | AB98: 1334 | AC98: 12 | AD98: 12 | AE98: TRUE | AF98: TRUE | AG98: 4.3595484 | AH98: 1.6666939 | AI98: 214 | AJ98: 318 | AK98: 6 | AL98: 6 | AM98: -4.5045045 | AN98: -3.1674208
A99: 5 | B99: 2014 | C99: 5199.41 | D99: 303314 | E99: 4856.9562 | F99: 3382.5037 | G99: 4 | H99: 4 | I99: 1.0705079 | J99: -0.55052307 | K99: -0.80027768 | L99: 1.5371483 | M99: 3.4142574 | N99: -4.6034779 | O99: -1.346395 | P99: 1079 | Q99: 4 | R99: 1104 | S99: 4 | T99: 60877.2 | U99: 4 | V99: 55.142391 | W99: TRUE | X99: TRUE | Y99: 3.5573696 | Z99: 3.6397924 | AA99: 1314 | AB99: 625 | AC99: 12 | AD99: 12 | AE99: TRUE | AF99: TRUE | AG99: 2.0605709 | AH99: 4.3321442 | AI99: 961 | AJ99: 258 | AK99: 6 | AL99: 6 | AM99: -18.867925 | AN99: 349.06542
A100: 5 | B100: 2015 | C100: 5262.02 | D100: 300797 | E100: 4936.127 | F100: 3412.164 | G100: 4 | H100: 4 | I100: 1.066022 | J100: 1.6300512 | K100: -0.41904547 | L100: 1.5421357 | M100: 0.87687132 | N100: 0.32445869 | O100: 1.2041751 | P100: 1147 | Q100: 4 | R100: 1153 | S100: 4 | T100: 61772.4 | U100: 4 | V100: 53.575369 | W100: TRUE | X100: TRUE | Y100: 3.8132029 | Z100: 3.8331499 | AA100: 1159 | AB100: 1365 | AC100: 12 | AD100: 12 | AE100: TRUE | AF100: TRUE | AG100: 4.5379442 | AH100: 3.8530969 | AI100: 619 | AJ100: 810 | AK100: 6 | AL100: 6 | AM100: 213.95349 | AN100: -35.587929
...

Sheet src_fact_hedonic_period
A1: city_id | B1: nbp_period_id | C1: hedonic_qoq_index | D1: hedonic_yoy_index | E1: hedonic_qoq_pct | F1: hedonic_yoy_pct | G1: secondary_transaction_yoy_pct | H1: headline_minus_hedonic_yoy_pp | I1: comparison_available | J1: opposite_direction
A2: 1 | B2: 20071 | C2: 117.53964 | E2: 17.53964 | I2: FALSE | J2: FALSE
A3: 2 | B3: 20071 | C3: 128.81098 | E3: 28.810976 | I3: FALSE | J3: FALSE
A4: 5 | B4: 20071 | C4: 129.48789 | E4: 29.487893 | I4: FALSE | J4: FALSE
A5: 6 | B5: 20071 | C5: 115.15004 | E5: 15.150037 | I5: FALSE | J5: FALSE
A6: 7 | B6: 20071 | C6: 95.46288 | E6: -4.53712 | I6: FALSE | J6: FALSE
A7: 8 | B7: 20071 | C7: 117.26893 | E7: 17.268926 | I7: FALSE | J7: FALSE
A8: 9 | B8: 20071 | C8: 100.65287 | E8: 0.65286692 | I8: FALSE | J8: FALSE
A9: 10 | B9: 20071 | I9: FALSE | J9: FALSE
A10: 11 | B10: 20071 | C10: 106.92194 | E10: 6.921944 | I10: FALSE | J10: FALSE
A11: 12 | B11: 20071 | C11: 115.05236 | E11: 15.052356 | I11: FALSE | J11: FALSE
A12: 13 | B12: 20071 | C12: 125.75405 | E12: 25.754048 | I12: FALSE | J12: FALSE
A13: 14 | B13: 20071 | C13: 109.74151 | E13: 9.7415107 | I13: FALSE | J13: FALSE
A14: 15 | B14: 20071 | C14: 107.62541 | E14: 7.62541 | I14: FALSE | J14: FALSE
A15: 16 | B15: 20071 | C15: 98.243475 | E15: -1.7565254 | I15: FALSE | J15: FALSE
A16: 17 | B16: 20071 | C16: 145.6957 | E16: 45.6957 | I16: FALSE | J16: FALSE
A17: 1 | B17: 20081 | C17: 98.595125 | D17: 124.25183 | E17: -1.4048745 | F17: 24.25183 | G17: 29.676503 | H17: 5.4246727 | I17: TRUE | J17: FALSE
A18: 2 | B18: 20081 | C18: 102.86885 | D18: 118.81657 | E18: 2.8688525 | F18: 18.816568 | G18: 22.725495 | H18: 3.9089268 | I18: TRUE | J18: FALSE
A19: 5 | B19: 20081 | C19: 96.29623 | D19: 104.98815 | E19: -3.7037704 | F19: 4.988146 | G19: 46.568558 | H19: 41.580412 | I19: TRUE | J19: FALSE
A20: 6 | B20: 20081 | C20: 104.67426 | D20: 135.65525 | E20: 4.6742567 | F20: 35.65525 | G20: 35.944092 | H20: 0.28884172 | I20: TRUE | J20: FALSE
A21: 7 | B21: 20081 | C21: 96.77582 | D21: 107.20706 | E21: -3.2241805 | F21: 7.207061 | G21: -0.60453053 | H21: -7.8115916 | I21: TRUE | J21: TRUE
A22: 8 | B22: 20081 | C22: 100.59483 | D22: 135.90722 | E22: 0.59482618 | F22: 35.907219 | G22: 35.253994 | H22: -0.65322517 | I22: TRUE | J22: FALSE
A23: 9 | B23: 20081 | C23: 103.47922 | D23: 129.88468 | E23: 3.4792192 | F23: 29.884682 | G23: 19.608446 | H23: -10.276236 | I23: TRUE | J23: FALSE
A24: 10 | B24: 20081 | C24: 97.690086 | E24: -2.3099136 | G24: 9.3538936 | I24: FALSE | J24: FALSE
A25: 11 | B25: 20081 | C25: 106.42202 | D25: 143.80165 | E25: 6.4220183 | F25: 43.801653 | G25: 32.520051 | H25: -11.281602 | I25: TRUE | J25: FALSE
A26: 12 | B26: 20081 | C26: 91.421144 | D26: 120.02275 | E26: -8.5788562 | F26: 20.022753 | G26: 4.6696535 | H26: -15.3531 | I26: TRUE | J26: FALSE
A27: 13 | B27: 20081 | C27: 100.23655 | D27: 117.14337 | E27: 0.23654616 | F27: 17.143367 | G27: 28.545512 | H27: 11.402146 | I27: TRUE | J27: FALSE
A28: 14 | B28: 20081 | C28: 98.955481 | D28: 113.56581 | E28: -1.0445188 | F28: 13.565808 | G28: 16.87933 | H28: 3.3135224 | I28: TRUE | J28: FALSE
A29: 15 | B29: 20081 | C29: 98.436285 | D29: 103.72684 | E29: -1.5637152 | F29: 3.7268404 | G29: 3.7652205 | H29: 0.038380105 | I29: TRUE | J29: FALSE
A30: 16 | B30: 20081 | C30: 98.79351 | D30: 136.61791 | E30: -1.2064903 | F30: 36.617907 | G30: 44.008721 | H30: 7.390814 | I30: TRUE | J30: FALSE
A31: 17 | B31: 20081 | C31: 95.541824 | D31: 114.92888 | E31: -4.4581756 | F31: 14.928885 | G31: 28.381234 | H31: 13.452349 | I31: TRUE | J31: FALSE
A32: 1 | B32: 20091 | C32: 96.367188 | D32: 96.745689 | E32: -3.6328125 | F32: -3.2543108 | G32: -8.1280039 | H32: -4.8736931 | I32: TRUE | J32: FALSE
A33: 2 | B33: 20091 | C33: 98.417409 | D33: 99.103586 | E33: -1.5825915 | F33: -0.89641434 | G33: -1.1558855 | H33: -0.25947116 | I33: TRUE | J33: FALSE
A34: 5 | B34: 20091 | C34: 84.100825 | D34: 118.95732 | E34: -15.899175 | F34: 18.957321 | G34: -2.3414212 | H34: -21.298742 | I34: TRUE | J34: TRUE
A35: 6 | B35: 20091 | C35: 94.51984 | D35: 95.604934 | E35: -5.4801596 | F35: -4.3950656 | G35: -3.9490866 | H35: 0.44597897 | I35: TRUE | J35: FALSE
A36: 7 | B36: 20091 | C36: 89.600622 | D36: 88.022817 | E36: -10.399378 | F36: -11.977183 | G36: -0.79486449 | H36: 11.182319 | I36: TRUE | J36: FALSE
... A301: 17 | B301: 20261 | C301: 101.18421 | D301: 102.82386 | E301: 1.1842119 | F301: 2.8238624 | G301: -0.48894003 | H301: -3.3128024 | I301: TRUE | J301: TRUE
A302: 1 | B302: 20072 | C302: 119.81838 | E302: 19.818377 | I302: FALSE | J302: FALSE
A303: 2 | B303: 20072 | C303: 105.56213 | E303: 5.5621302 | I303: FALSE | J303: FALSE
A304: 5 | B304: 20072 | C304: 124.9229 | E304: 24.9229 | I304: FALSE | J304: FALSE
A305: 6 | B305: 20072 | C305: 119.82297 | E305: 19.822974 | I305: FALSE | J305: FALSE
A306: 7 | B306: 20072 | C306: 116.65297 | E306: 16.652971 | I306: FALSE | J306: FALSE
A307: 8 | B307: 20072 | C307: 114.62002 | E307: 14.620018 | I307: FALSE | J307: FALSE
A308: 9 | B308: 20072 | C308: 115.77184 | E308: 15.771836 | I308: FALSE | J308: FALSE
A309: 10 | B309: 20072 | I309: FALSE | J309: FALSE
A310: 11 | B310: 20072 | C310: 134.29752 | E310: 34.297521 | I310: FALSE | J310: FALSE
A311: 12 | B311: 20072 | C311: 109.67008 | E311: 9.6700796 | I311: FALSE | J311: FALSE
A312: 13 | B312: 20072 | C312: 105.36586 | E312: 5.365859 | I312: FALSE | J312: FALSE
A313: 14 | B313: 20072 | C313: 109.49884 | E313: 9.4988392 | I313: FALSE | J313: FALSE
A314: 15 | B314: 20072 | C314: 108.73004 | E314: 8.730045 | I314: FALSE | J314: FALSE
A315: 16 | B315: 20072 | C315: 121.75673 | E315: 21.756731 | I315: FALSE | J315: FALSE
A316: 17 | B316: 20072 | C316: 106.714 | E316: 6.7139966 | I316: FALSE | J316: FALSE
A317: 1 | B317: 20082 | C317: 97.678554 | D317: 101.2928 | E317: -2.3214461 | F317: 1.2928014 | G317: 14.584722 | H317: 13.291921 | I317: TRUE | J317: FALSE
A318: 2 | B318: 20082 | C318: 103.88446 | D318: 116.92825 | E318: 3.8844622 | F318: 16.928251 | G318: 4.4244168 | H318: -12.503834 | I318: TRUE | J318: FALSE
A319: 5 | B319: 20082 | C319: 148.65392 | D319: 124.93226 | E319: 48.653924 | F319: 24.932257 | G319: 22.971178 | H319: -1.9610789 | I319: TRUE | J319: FALSE
A320: 6 | B320: 20082 | C320: 105.21688 | D320: 119.11924 | E320: 5.216877 | F320: 19.119242 | G320: 12.136608 | H320: -6.9826334 | I320: TRUE | J320: FALSE
A321: 7 | B321: 20082 | C321: 102.16199 | D321: 93.889482 | E321: 2.1619936 | F321: -6.1105177 | G321: -5.01427 | H321: 1.0962477 | I321: TRUE | J321: FALSE
A322: 8 | B322: 20082 | C322: 103.86909 | D322: 123.15963 | E322: 3.869087 | F322: 23.159627 | G322: 20.236363 | H322: -2.9232642 | I322: TRUE | J322: FALSE
A323: 9 | B323: 20082 | C323: 95.157416 | D323: 106.75732 | E323: -4.8425835 | F323: 6.7573187 | G323: 0.070032604 | H323: -6.6872861 | I323: TRUE | J323: FALSE
A324: 10 | B324: 20082 | C324: 101.86363 | D324: 101.24064 | E324: 1.8636306 | F324: 1.2406382 | G324: -3.8053321 | H324: -5.0459703 | I324: TRUE | J324: TRUE
A325: 11 | B325: 20082 | C325: 96.360153 | D325: 103.17949 | E325: -3.6398467 | F325: 3.1794872 | G325: 6.0816797 | H325: 2.9021925 | I325: TRUE | J325: FALSE
A326: 12 | B326: 20082 | C326: 102.18009 | D326: 111.82573 | E326: 2.1800948 | F326: 11.825726 | G326: 4.2357246 | H326: -7.5900015 | I326: TRUE | J326: FALSE
A327: 13 | B327: 20082 | C327: 99.538948 | D327: 110.66514 | E327: -0.46105211 | F327: 10.665139 | G327: 7.7606226 | H327: -2.9045167 | I327: TRUE | J327: FALSE
A328: 14 | B328: 20082 | C328: 97.705924 | D328: 101.33488 | E328: -2.2940758 | F328: 1.3348845 | G328: 5.9925538 | H328: 4.6576693 | I328: TRUE | J328: FALSE
... A601: 17 | B601: 20262 | C601: 99.402292 | D601: 100.80214 | E601: -0.59770761 | F601: 0.80213983 | G601: -1.6521647 | H601: -2.4543045 | I601: TRUE | J601: TRUE
A602: 1 | B602: 20063 | I602: FALSE | J602: FALSE
A603: 2 | B603: 20063 | I603: FALSE | J603: FALSE
A604: 5 | B604: 20063 | I604: FALSE | J604: FALSE
A605: 6 | B605: 20063 | I605: FALSE | J605: FALSE
A606: 7 | B606: 20063 | I606: FALSE | J606: FALSE
A607: 8 | B607: 20063 | I607: FALSE | J607: FALSE
A608: 9 | B608: 20063 | I608: FALSE | J608: FALSE
A609: 10 | B609: 20063 | I609: FALSE | J609: FALSE
A610: 11 | B610: 20063 | I610: FALSE | J610: FALSE
A611: 12 | B611: 20063 | I611: FALSE | J611: FALSE
A612: 13 | B612: 20063 | I612: FALSE | J612: FALSE
A613: 14 | B613: 20063 | I613: FALSE | J613: FALSE
... A616: 17 | B616: 20063 | I616: FALSE | J616: FALSE
A617: 1 | B617: 20073 | C617: 105.60569 | D617: 173.94808 | E617: 5.6056918 | F617: 73.948077 | G617: 75.949904 | H617: 2.0018274 | I617: TRUE | J617: FALSE
A618: 2 | B618: 20073 | C618: 114.46188 | D618: 164.41224 | E618: 14.461883 | F618: 64.412238 | G618: 63.850086 | H618: -0.56215246 | I618: TRUE | J618: FALSE
A619: 5 | B619: 20073 | C619: 111.00776 | D619: 177.42918 | E619: 11.007756 | F619: 77.429178 | G619: 90.439734 | H619: 13.010555 | I619: TRUE | J619: FALSE
A620: 6 | B620: 20073 | C620: 112.92549 | D620: 173.01249 | E620: 12.925489 | F620: 73.012486 | G620: 56.644194 | H620: -16.368293 | I620: TRUE | J620: FALSE
A621: 7 | B621: 20073 | C621: 96.967357 | D621: 127.24727 | E621: -3.0326428 | F621: 27.247267 | G621: 44.952785 | H621: 17.705518 | I621: TRUE | J621: FALSE
A622: 8 | B622: 20073 | C622: 108.80365 | D622: 148.08602 | E622: 8.8036469 | F622: 48.08602 | G622: 56.369368 | H622: 8.2833484 | I622: TRUE | J622: FALSE
A623: 9 | B623: 20073 | C623: 102.24358 | D623: 136.81742 | E623: 2.2435846 | F623: 36.817419 | G623: 58.931788 | H623: 22.114369 | I623: TRUE | J623: FALSE
A624: 10 | B624: 20073 | C624: 108.1884 | E624: 8.1883981 | G624: 37.334508 | I624: FALSE | J624: FALSE
A625: 11 | B625: 20073 | C625: 103.28205 | D625: 171.46263 | E625: 3.2820513 | F625: 71.462626 | G625: 71.142291 | H625: -0.32033419 | I625: TRUE | J625: FALSE
A626: 12 | B626: 20073 | C626: 107.88382 | D626: 152.94118 | E626: 7.8838174 | F626: 52.941176 | G626: 60.375924 | H626: 7.4347478 | I626: TRUE | J626: FALSE
A627: 13 | B627: 20073 | C627: 111.17119 | D627: 153.36217 | E627: 11.17119 | F627: 53.36217 | G627: 66.704536 | H627: 13.342366 | I627: TRUE | J627: FALSE
A628: 14 | B628: 20073 | C628: 106.14087 | D628: 155.49181 | E628: 6.1408687 | F628: 55.491806 | G628: 48.374349 | H628: -7.1174567 | I628: TRUE | J628: FALSE
A629: 15 | B629: 20073 | C629: 112.2672 | D629: 135.68427 | E629: 12.267201 | F629: 35.684275 | G629: 51.993713 | H629: 16.309439 | I629: TRUE | J629: FALSE
A630: 16 | B630: 20073 | C630: 111.97046 | D630: 144.31034 | E630: 11.970463 | F630: 44.310336 | G630: 69.159051 | H630: 24.848715 | I630: TRUE | J630: FALSE
A631: 17 | B631: 20073 | C631: 109.41303 | D631: 209.97497 | E631: 9.4130262 | F631: 109.97497 | G631: 111.09251 | H631: 1.1175435 | I631: TRUE | J631: FALSE
A632: 1 | B632: 20083 | C632: 102.84566 | D632: 98.645486 | E632: 2.8456578 | F632: -1.3545139 | G632: 2.476147 | H632: 3.8306609 | I632: TRUE | J632: TRUE
A633: 2 | B633: 20083 | C633: 97.986577 | D633: 100.09794 | E633: -2.0134228 | F633: 0.097943193 | G633: -0.89215314 | H633: -0.99009633 | I633: TRUE | J633: TRUE
A634: 5 | B634: 20083 | C634: 88.638353 | D634: 99.756899 | E634: -11.361647 | F634: -0.24310143 | G634: 2.4029232 | H634: 2.6460246 | I634: TRUE | J634: TRUE
A635: 6 | B635: 20083 | C635: 95.725347 | D635: 100.9757 | E635: -4.2746528 | F635: 0.97570458 | G635: 11.912448 | H635: 10.936744 | I635: TRUE | J635: FALSE
A636: 7 | B636: 20083 | C636: 91.03335 | D636: 88.143828 | E636: -8.9666503 | F636: -11.856172 | G636: -8.0223229 | H636: 3.8338489 | I636: TRUE | J636: FALSE
... A901: 17 | B901: 20253 | C901: 96.880716 | D901: 103.25791 | E901: -3.1192837 | F901: 3.2579139 | G901: 2.8517656 | H901: -0.40614835 | I901: TRUE | J901: FALSE
A902: 1 | B902: 20064 | C902: 116.95654 | E902: 16.956541 | I902: FALSE | J902: FALSE
...

Sheet src_fact_price_period
A1: city_id | B1: nbp_period_id | C1: primary_transaction_price_pln_m2 | D1: secondary_transaction_price_pln_m2 | E1: primary_transaction_yoy_pct | F1: primary_yoy_4p_avg_pct | G1: primary_momentum_change_pp | H1: secondary_transaction_yoy_pct | I1: secondary_yoy_4p_avg_pct | J1: secondary_momentum_change_pp | K1: primary_secondary_premium_pct | L1: primary_transaction_methodology_break | M1: primary_transaction_methodology_note
A2: 1 | B2: 20063 | C2: 3008 | D2: 2464.1162 | K2: 22.072164 | L2: FALSE
A3: 1 | B3: 20064 | C3: 3117 | D3: 2922.1044 | K3: 6.6697009 | L3: FALSE
A4: 1 | B4: 20071 | C4: 3500 | D4: 3377.3927 | K4: 3.6302341 | L4: FALSE
A5: 1 | B5: 20072 | C5: 4422 | D5: 3950.2648 | K5: 11.941863 | L5: FALSE
A6: 1 | B6: 20073 | C6: 4651 | D6: 4335.6101 | E6: 54.621011 | H6: 75.949904 | K6: 7.2744054 | L6: FALSE
A7: 1 | B7: 20074 | C7: 5079 | D7: 4455.3638 | E7: 62.94514 | H7: 52.471069 | K7: 13.997425 | L7: FALSE
A8: 1 | B8: 20081 | C8: 5160 | D8: 4379.6848 | E8: 47.428571 | H8: 29.676503 | K8: 17.816698 | L8: FALSE
A9: 1 | B9: 20082 | C9: 4973 | D9: 4526.4 | E9: 12.460425 | F9: 44.363787 | H9: 14.584722 | I9: 43.17055 | K9: 9.8665618 | L9: FALSE
A10: 1 | B10: 20083 | C10: 5141 | D10: 4442.9662 | E10: 10.535369 | F10: 33.342376 | H10: 2.476147 | I10: 24.80211 | K10: 15.710985 | L10: FALSE
A11: 1 | B11: 20084 | C11: 5177 | D11: 4292.9861 | E11: 1.9295137 | F11: 18.08847 | H11: -3.6445436 | I11: 10.773207 | K11: 20.592051 | L11: FALSE
A12: 1 | B12: 20091 | C12: 5005 | D12: 4023.7038 | E12: -3.003876 | F12: 5.4803579 | H12: -8.1280039 | I12: 1.3220804 | K12: 24.387882 | L12: FALSE
A13: 1 | B13: 20092 | C13: 4976 | D13: 4049.6453 | E13: 0.060325759 | F13: 2.3803331 | G13: -41.983454 | H13: -10.532756 | I13: -4.9572892 | J13: -48.127839 | K13: 22.87496 | L13: FALSE
A14: 1 | B14: 20093 | C14: 4787 | D14: 4103.0214 | E14: -6.8858199 | F14: -1.9749641 | G14: -35.31734 | H14: -7.651304 | I14: -7.489152 | J14: -32.291262 | K14: 16.670121 | L14: FALSE
A15: 1 | B15: 20094 | C15: 4838 | D15: 3996.9328 | E15: -6.5481939 | F15: -4.094391 | G15: -22.182861 | H15: -6.89621 | I15: -8.3020686 | J15: -19.075276 | K15: 21.042816 | L15: FALSE
A16: 1 | B16: 20101 | C16: 4790 | D16: 4070.7274 | E16: -4.2957043 | F16: -4.4173481 | G16: -9.897706 | H16: 1.1686634 | I16: -5.9779018 | J16: -7.2999822 | K16: 17.669388 | L16: FALSE
A17: 1 | B17: 20102 | C17: 4802 | D17: 4161.3169 | E17: -3.4967846 | F17: -5.3066257 | G17: -7.6869587 | H17: 2.7575649 | I17: -2.6553214 | J17: 2.3019678 | K17: 15.396163 | L17: FALSE
A18: 1 | B18: 20103 | C18: 4732 | D18: 4176.8664 | E18: -1.1489451 | F18: -3.872407 | G18: -1.8974429 | H18: 1.7997717 | I18: -0.2925525 | J18: 7.1965995 | K18: 13.290672 | L18: FALSE
A19: 1 | B19: 20104 | C19: 4755 | D19: 4194.7535 | E19: -1.715585 | F19: -2.6642547 | G19: 1.4301363 | H19: 4.949314 | I19: 2.6688285 | J19: 10.970897 | K19: 13.355885 | L19: FALSE
A20: 1 | B20: 20111 | C20: 4821 | D20: 4395.7826 | E20: 0.64718163 | F20: -1.4285332 | G20: 2.9888149 | H20: 7.9851865 | I20: 4.3729593 | J20: 10.350861 | K20: 9.6733046 | L20: FALSE
A21: 1 | B21: 20112 | C21: 4782 | D21: 4382.8099 | E21: -0.41649313 | F21: -0.65846038 | G21: 4.6481653 | H21: 5.3226661 | I21: 5.0142346 | J21: 7.669556 | K21: 9.1080869 | L21: FALSE
A22: 1 | B22: 20113 | C22: 4843 | D22: 4190.0643 | E22: 2.3457312 | F22: 0.21520868 | G22: 4.0876156 | H22: 0.31597611 | I22: 4.6432857 | J22: 4.9358382 | K22: 15.582952 | L22: FALSE
A23: 1 | B23: 20114 | C23: 4601 | D23: 4265.5884 | E23: -3.2386961 | F23: -0.1655691 | G23: 2.4986856 | H23: 1.6886544 | I23: 3.8281208 | J23: 1.1592923 | K23: 7.8631961 | L23: FALSE
A24: 1 | B24: 20121 | C24: 4577 | D24: 4241.5969 | E24: -5.0611906 | F24: -1.5926622 | G24: -0.16412893 | H24: -3.5075825 | I24: 0.95492852 | J24: -3.4180307 | K24: 7.9074733 | L24: FALSE
... A81: 1 | B81: 20262 | C81: 10926.219 | D81: 9403.1318 | E81: 4.485637 | F81: 1.9246065 | G81: -8.1815324 | H81: -0.1766421 | I81: 0.65780585 | J81: -13.318624 | K81: 16.197656 | L81: FALSE
A82: 2 | B82: 20063 | C82: 2663 | D82: 2371.632 | K82: 12.285549 | L82: FALSE
A83: 2 | B83: 20064 | C83: 2811 | D83: 2560.4466 | K83: 9.7855331 | L83: FALSE
A84: 2 | B84: 20071 | C84: 3017 | D84: 3056.2226 | K84: -1.2833677 | L84: FALSE
A85: 2 | B85: 20072 | C85: 4092 | D85: 3706.4495 | K85: 10.402153 | L85: FALSE
A86: 2 | B86: 20073 | C86: 4466 | D86: 3885.921 | E86: 67.705595 | H86: 63.850086 | K86: 14.927708 | L86: FALSE
A87: 2 | B87: 20074 | C87: 4582 | D87: 3888.704 | E87: 63.00249 | H87: 51.876003 | K87: 17.828458 | L87: FALSE
A88: 2 | B88: 20081 | C88: 4540 | D88: 3750.7643 | E88: 50.48061 | H88: 22.725495 | K88: 21.041997 | L88: FALSE
A89: 2 | B89: 20082 | C89: 4982 | D89: 3870.4382 | E89: 21.749756 | F89: 50.734613 | H89: 4.4244168 | I89: 35.719 | K89: 28.719274 | L89: FALSE
A90: 2 | B90: 20083 | C90: 4670 | D90: 3851.2527 | E90: 4.5678459 | F90: 34.950175 | H90: -0.89215314 | I90: 19.53344 | K90: 21.259247 | L90: FALSE
A91: 2 | B91: 20084 | C91: 4749 | D91: 3891.5531 | E91: 3.6446966 | F91: 20.110727 | H91: 0.073264999 | I91: 6.5827559 | K91: 22.03354 | L91: FALSE
A92: 2 | B92: 20091 | C92: 5023 | D92: 3707.4097 | E92: 10.638767 | F92: 10.150266 | H92: -1.1558855 | I92: 0.6124108 | K92: 35.485429 | L92: FALSE
A93: 2 | B93: 20092 | C93: 4835 | D93: 3586.6771 | E93: -2.9506222 | F93: 3.9751717 | G93: -46.759441 | H93: -7.3314999 | I93: -2.3265684 | J93: -38.045568 | K93: 34.804442 | L93: FALSE
A94: 2 | B94: 20093 | C94: 4757 | D94: 3745.6709 | E94: 1.862955 | F94: 3.298949 | G94: -31.651226 | H94: -2.7414923 | I94: -2.7889032 | J94: -22.322344 | K94: 26.999946 | L94: FALSE
A95: 2 | B95: 20094 | C95: 4694 | D95: 3753.7165 | E95: -1.1581386 | F95: 2.0982402 | G95: -18.012487 | H95: -3.5419423 | I95: -3.692705 | J95: -10.275461 | K95: 25.0494 | L95: FALSE
A96: 2 | B96: 20101 | C96: 4524 | D96: 3819.2942 | E96: -9.9343022 | F96: -3.045027 | G96: -13.195293 | H96: 3.0178603 | I96: -2.6492685 | J96: -3.2616793 | K96: 18.451205 | L96: FALSE
A97: 2 | B97: 20102 | C97: 4856 | D97: 3808.7458 | E97: 0.43433299 | F97: -2.1987882 | G97: -6.1739599 | H97: 6.1914897 | I97: 0.73147888 | J97: 3.0580473 | K97: 27.496038 | L97: FALSE
A98: 2 | B98: 20103 | C98: 4954 | D98: 3811.2278 | E98: 4.1412655 | F98: -1.6292106 | G98: -4.9281596 | H98: 1.750206 | I98: 1.8544035 | J98: 4.6433066 | K98: 29.984357 | L98: FALSE
A99: 2 | B99: 20104 | C99: 4606 | D99: 3799.2434 | E99: -1.8747337 | F99: -1.8083594 | G99: -3.9065995 | H99: 1.2128479 | I99: 3.043101 | J99: 6.735806 | K99: 21.234665 | L99: FALSE
A100: 2 | B100: 20111 | C100: 4730 | D100: 3871.9923 | E100: 4.5534925 | F100: 1.8135893 | G100: 4.8586163 | H100: 1.3797878 | I100: 2.6335829 | J100: 5.2828514 | K100: 22.159332 | L100: FALSE
A101: 2 | B101: 20112 | C101: 4635 | D101: 3826.5515 | E101: -4.5510708 | F101: 0.56723836 | G101: 2.7660265 | H101: 0.46749548 | I101: 1.2025843 | J101: 0.47110543 | K101: 21.127338 | L101: FALSE
A102: 2 | B102: 20113 | C102: 4575 | D102: 3745.8833 | E102: -7.6503835 | F102: -2.3806739 | G102: -0.75146333 | H102: -1.7145276 | I102: 0.33640089 | J102: -1.5180026 | K102: 22.134078 | L102: FALSE
A103: 2 | B103: 20114 | C103: 4626 | D103: 3654.5934 | E103: 0.43421624 | F103: -1.8034364 | G103: 0.004922944 | H103: -3.8073372 | I103: -0.91864538 | J103: -3.9617464 | K103: 26.58043 | L103: FALSE
A104: 2 | B104: 20121 | C104: 4520 | D104: 3609.9434 | E104: -4.4397463 | F104: -4.0517461 | G104: -5.8653354 | H104: -6.7678062 | I104: -2.9555439 | J104: -5.5891268 | K104: 25.209719 | L104: FALSE
... A161: 2 | B161: 20262 | C161: 10774.886 | D161: 8341.8674 | E161: 10.450538 | F161: 13.545044 | G161: 6.4740335 | H161: 6.8922016 | I161: 1.864496 | J161: -3.2718332 | K161: 29.166357 | L161: FALSE
A162: 3 | B162: 20063 | C162: 3494 | D162: 3493.2042 | K162: 0.02278194 | L162: FALSE
A163: 3 | B163: 20064 | C163: 5252 | D163: 3893.9157 | K163: 34.877085 | L163: FALSE
A164: 3 | B164: 20071 | C164: 5490 | D164: 4666.1619 | K164: 17.655583 | L164: FALSE
A165: 3 | B165: 20072 | C165: 7137 | D165: 5513.3821 | K165: 29.448673 | L165: FALSE
A166: 3 | B166: 20073 | C166: 7440 | D166: 5793.9561 | E166: 112.93646 | H166: 65.863653 | K166: 28.409672 | L166: FALSE
A167: 3 | B167: 20074 | C167: 6294 | D167: 5966.9612 | E167: 19.840061 | H167: 53.238068 | K167: 5.4808262 | L167: FALSE
A168: 3 | B168: 20081 | C168: 6473 | D168: 6072.4447 | E168: 17.905282 | H168: 30.13789 | K168: 6.5962779 | L168: FALSE
A169: 3 | B169: 20082 | C169: 7740 | D169: 6025.0556 | E169: 8.4489281 | F169: 39.782683 | H169: 9.2805739 | I169: 39.630046 | K169: 28.463544 | L169: FALSE
A170: 3 | B170: 20083 | C170: 7042 | D170: 5895.655 | E170: -5.3494624 | F170: 10.211202 | H170: 1.7552583 | I170: 23.602948 | K170: 19.443896 | L170: FALSE
A171: 3 | B171: 20084 | C171: 6193 | D171: 5804.3497 | E171: -1.6047029 | F171: 4.8500113 | H171: -2.725198 | I171: 9.6121311 | K171: 6.6958454 | L171: FALSE
A172: 3 | B172: 20091 | C172: 5309 | D172: 5598.3101 | E172: -17.982388 | F172: -4.1219064 | H172: -7.8079683 | I172: 0.12566647 | K172: -5.1678116 | L172: FALSE
A173: 3 | B173: 20092 | C173: 5907 | D173: 5446.7323 | E173: -23.682171 | F173: -12.154681 | G173: -51.937365 | H173: -9.5986396 | I173: -4.5941369 | J173: -44.224183 | K173: 8.4503463 | L173: FALSE
A174: 3 | B174: 20093 | C174: 5804 | D174: 5486.0487 | E174: -17.580233 | F174: -15.212374 | G174: -25.423576 | H174: -6.9475946 | I174: -6.7698502 | J174: -30.372798 | K174: 5.795633 | L174: FALSE
A175: 3 | B175: 20094 | C175: 5476 | D175: 5551.7728 | E175: -11.577588 | F175: -17.705595 | G175: -22.555606 | H175: -4.3515117 | I175: -7.1764286 | J175: -16.78856 | K175: -1.364839 | L175: FALSE
A176: 3 | B176: 20101 | C176: 5839.4534 | D176: 5636.8963 | E176: 9.9915879 | F176: -10.712101 | G176: -6.5901944 | H176: 0.68924618 | I176: -5.0521249 | J176: -5.1777914 | K176: 3.5934163 | L176: FALSE
A177: 3 | B177: 20102 | C177: 5677.5624 | D177: 5571.2901 | E177: -3.8841638 | F177: -5.7625991 | G177: 6.392082 | H177: 2.2868366 | I177: -2.0807559 | J177: 2.513381 | K177: 1.9074992 | L177: FALSE
A178: 3 | B178: 20103 | C178: 5272.0494 | D178: 5499.5774 | E178: -9.1652416 | F178: -3.6588513 | G178: 11.553522 | H178: 0.24660047 | I178: -0.28220711 | J178: 6.487643 | K178: -4.1371905 | L178: FALSE
A179: 3 | B179: 20104 | C179: 5216 | D179: 5359.9626 | E179: -4.7479912 | F179: -1.9514522 | G179: 15.754143 | H179: -3.4549351 | I179: -0.05806296 | J179: 7.1183656 | K179: -2.6858884 | L179: FALSE
A180: 3 | B180: 20111 | C180: 5692 | D180: 5506.8654 | E180: -2.5251234 | F180: -5.08063 | G180: 5.6314708 | H180: -2.306781 | I180: -0.80706977 | J180: 4.2450552 | K180: 3.3618871 | L180: FALSE
A181: 3 | B181: 20112 | C181: 5661 | D181: 5568.1861 | E181: -0.29171754 | F181: -4.1825184 | G181: 1.5800806 | H181: -0.05571415 | I181: -1.3927075 | J181: 0.68804842 | K181: 1.66686 | L181: FALSE
A182: 3 | B182: 20113 | C182: 5479 | D182: 5431.6317 | E182: 3.9254303 | F182: -0.90985046 | G182: 2.7490008 | H182: -1.2354708 | I182: -1.7632253 | J182: -1.4810182 | K182: 0.87208234 | L182: FALSE
A183: 3 | B183: 20114 | C183: 5506 | D183: 5279.7277 | E183: 5.559816 | F183: 1.6671013 | G183: 3.6185535 | H183: -1.4969311 | I183: -1.2737243 | J183: -1.2156613 | K183: 4.2856819 | L183: FALSE
A184: 3 | B184: 20121 | C184: 5594 | D184: 5310.0368 | E184: -1.7217147 | F184: 1.8679535 | G184: 6.9485835 | H184: -3.5742398 | I184: -1.590589 | J184: -0.78351919 | K184: 5.3476686 | L184: FALSE
... A241: 3 | B241: 20262 | C241: 14490.615 | D241: 14034.642 | E241: 2.897908 | F241: 7.6107044 | G241: -0.55098668 | H241: 4.6129284 | I241: 4.4716399 | J241: -5.9369519 | K241: 3.248908 | L241: FALSE
A242: 4 | B242: 20063 | C242: 4467 | D242: 3555.291 | K242: 25.643722 | L242: FALSE
A243: 4 | B243: 20064 | C243: 5284 | D243: 3983.2253 | K243: 32.656319 | L243: FALSE
A244: 4 | B244: 20071 | C244: 5797 | D244: 4928.5203 | K244: 17.62151 | L244: FALSE
A245: 4 | B245: 20072 | C245: 6992 | D245: 5425.1462 | K245: 28.88132 | L245: FALSE
A246: 4 | B246: 20073 | C246: 7238 | D246: 5930.6852 | E246: 62.032684 | H246: 66.812931 | K246: 22.043234 | L246: FALSE
A247: 4 | B247: 20074 | C247: 7495 | D247: 6010.9749 | E247: 41.843301 | H247: 50.907229 | K247: 24.688593 | L247: FALSE
A248: 4 | B248: 20081 | C248: 7301 | D248: 6046.8281 | E248: 25.944454 | H248: 22.690538 | K248: 20.740989 | L248: FALSE
A249: 4 | B249: 20082 | C249: 7209 | D249: 6015.8779 | E249: 3.1035469 | F249: 33.230996 | H249: 10.88877 | I249: 37.824867 | K249: 19.832885 | L249: FALSE
A250: 4 | B250: 20083 | C250: 6694 | D250: 5733.4709 | E250: -7.5158884 | F250: 15.843853 | H250: -3.3253204 | I250: 20.290304 | K250: 16.753012 | L250: FALSE
A251: 4 | B251: 20084 | C251: 6384 | D251: 5829.6682 | E251: -14.823215 | F251: 1.6772243 | H251: -3.0162605 | I251: 6.8094317 | K251: 9.5088046 | L251: FALSE
A252: 4 | B252: 20091 | C252: 6241 | D252: 5693.3394 | E252: -14.518559 | F252: -8.438529 | H252: -5.8458525 | I252: -0.32466587 | K252: 9.6193208 | L252: FALSE
A253: 4 | B253: 20092 | C253: 5891 | D253: 5487.1326 | E253: -18.282702 | F253: -13.785091 | G253: -47.016088 | H253: -8.7891614 | I253: -5.2441487 | J253: -43.069016 | K253: 7.3602624 | L253: FALSE
A254: 4 | B254: 20093 | C254: 5504 | D254: 5334.6453 | E254: -17.777114 | F254: -16.350398 | G254: -32.194251 | H254: -6.9560939 | I254: -6.1518421 | J254: -26.442146 | K254: 3.1746199 | L254: FALSE
A255: 4 | B255: 20094 | C255: 5774 | D255: 5328.6516 | E255: -9.5551378 | F255: -15.033378 | G255: -16.710603 | H255: -8.5942568 | I255: -7.5463411 | J255: -14.355773 | K255: 8.3576195 | L255: FALSE
A256: 4 | B256: 20101 | C256: 5495.145 | D256: 5402.2036 | E256: -11.950889 | F256: -14.391461 | G256: -5.9529317 | H256: -5.1136216 | I256: -7.3632834 | J256: -7.0386176 | K256: 1.7204357 | L256: FALSE
A257: 4 | B257: 20102 | C257: 5277.7122 | D257: 5336.3315 | E257: -10.410589 | F257: -12.423432 | G257: 1.361659 | H257: -2.7482685 | I257: -5.8530602 | J257: -0.60891153 | K257: -1.0984939 | L257: FALSE
A258: 4 | B258: 20103 | C258: 5460.6524 | D258: 5394.6985 | E258: -0.7875647 | F258: -8.176045 | G258: 8.1743526 | H258: 1.12572 | I258: -3.8326068 | J258: 2.3192353 | K258: 1.2225704 | L258: FALSE
A259: 4 | B259: 20104 | C259: 5617 | D259: 5329.8903 | E259: -2.7190856 | F259: -6.467032 | G259: 8.5663463 | H259: 0.023247293 | I259: -1.6782307 | J259: 5.8681104 | K259: 5.3867836 | L259: FALSE
A260: 4 | B260: 20111 | C260: 6004 | D260: 5305.8747 | E260: 9.2600829 | F260: -1.164289 | G260: 13.227172 | H260: -1.7831414 | I260: -0.84561065 | J260: 6.5176728 | K260: 13.157592 | L260: FALSE
A261: 4 | B261: 20112 | C261: 6205 | D261: 5311.283 | E261: 17.569881 | F261: 5.8308285 | G261: 18.254261 | H261: -0.46939461 | I261: -0.27589217 | J261: 5.577168 | K261: 16.826762 | L261: FALSE
A262: 4 | B262: 20113 | C262: 6430 | D262: 5254.6766 | E262: 17.751497 | F262: 10.465594 | G262: 18.641639 | H262: -2.5955461 | I262: -1.2062087 | J262: 2.626398 | K262: 22.367189 | L262: FALSE
A263: 4 | B263: 20114 | C263: 6313.1293 | D263: 5353.4944 | E263: 12.393258 | F263: 14.24368 | G263: 20.710712 | H263: 0.44286149 | I263: -1.1013052 | J263: 0.57692557 | K263: 17.925393 | L263: FALSE
A264: 4 | B264: 20121 | C264: 6106 | D264: 5232.7075 | E264: 1.6988674 | F264: 12.353376 | G264: 13.517665 | H264: -1.3789846 | I264: -1.000266 | J264: -0.15465531 | K264: 16.689115 | L264: FALSE
... A301: 4 | B301: 20212 | C301: 9824.3989 | D301: 8291.617 | E301: 23.200062 | F301: 9.1394134 | G301: 5.1910284 | H301: 8.8975148 | I301: 6.5530791 | J301: -3.6316344 | K301: 18.485924 | L301: FALSE
A302: 4 | B302: 20213 | C302: 9738.8831 | D302: 8434.6306 | E302: 18.183502 | F302: 13.927772 | G302: 13.266245 | H302: 8.8178598 | I302: 6.9291322 | J302: -2.1635867 | K302: 15.463067 | L302: TRUE | M302: Gdynia primary transaction-price weighting methodology changed from 2021Q3.
A303: 4 | B303: 20214 | C303: 9927.3253 | D303: 8701.0505 | E303: 22.064702 | F303: 19.115324 | G303: 18.842834 | H303: 14.086887 | I303: 9.1682765 | J303: 1.1303251 | K303: 14.093411 | L303: FALSE
A304: 4 | B304: 20221 | C304: 9830.244 | D304: 8915.7089 | E304: 5.4194587 | F304: 17.216931 | G304: 14.507875 | H304: 13.720502 | I304: 11.380691 | J304: 4.8616479 | K304: 10.25757 | L304: FALSE
...

Sheet helper_report
A1: display_order_city_id | D1: current_h1_unique_rank | F1: City | G1: ="H1 "&(src_city_snapshot!$AW$2-1) -> H1 2025 | H1: ="H1 "&src_city_snapshot!$AW$2 -> H1 2026
A2: 1 | D2: =RANK('City Comparison'!I8,'City Comparison'!$I$8:$I$24,0)+COUNTIF('City Comparison'!$I$8:I8,'City Comparison'!I8)-1 -> 1 | F2: {=INDEX('City Comparison'!$A$8:$A$24,MATCH(ROWS($F$2:F2),$D$2:$D$18,0))} -> Warszawa | G2: {=INDEX('City Comparison'!$H$8:$H$24,MATCH(ROWS($F$2:F2),$D$2:$D$18,0))} -> 8300 | H2: {=INDEX('City Comparison'!$I$8:$I$24,MATCH(ROWS($F$2:F2),$D$2:$D$18,0))} -> 6867
A3: 2 | D3: =RANK('City Comparison'!I9,'City Comparison'!$I$8:$I$24,0)+COUNTIF('City Comparison'!$I$8:I9,'City Comparison'!I9)-1 -> 2 | F3: {=INDEX('City Comparison'!$A$8:$A$24,MATCH(ROWS($F$2:F3),$D$2:$D$18,0))} -> Kraków | G3: {=INDEX('City Comparison'!$H$8:$H$24,MATCH(ROWS($F$2:F3),$D$2:$D$18,0))} -> 2731 | H3: {=INDEX('City Comparison'!$I$8:$I$24,MATCH(ROWS($F$2:F3),$D$2:$D$18,0))} -> 4501
A4: 3 | D4: =RANK('City Comparison'!I10,'City Comparison'!$I$8:$I$24,0)+COUNTIF('City Comparison'!$I$8:I10,'City Comparison'!I10)-1 -> 6 | F4: {=INDEX('City Comparison'!$A$8:$A$24,MATCH(ROWS($F$2:F4),$D$2:$D$18,0))} -> Wrocław | G4: {=INDEX('City Comparison'!$H$8:$H$24,MATCH(ROWS($F$2:F4),$D$2:$D$18,0))} -> 3481 | H4: {=INDEX('City Comparison'!$I$8:$I$24,MATCH(ROWS($F$2:F4),$D$2:$D$18,0))} -> 3182
A5: 4 | D5: =RANK('City Comparison'!I11,'City Comparison'!$I$8:$I$24,0)+COUNTIF('City Comparison'!$I$8:I11,'City Comparison'!I11)-1 -> 3 | F5: {=INDEX('City Comparison'!$A$8:$A$24,MATCH(ROWS($F$2:F5),$D$2:$D$18,0))} -> Łódź | G5: {=INDEX('City Comparison'!$H$8:$H$24,MATCH(ROWS($F$2:F5),$D$2:$D$18,0))} -> 2263 | H5: {=INDEX('City Comparison'!$I$8:$I$24,MATCH(ROWS($F$2:F5),$D$2:$D$18,0))} -> 2602
A6: 5 | D6: =RANK('City Comparison'!I12,'City Comparison'!$I$8:$I$24,0)+COUNTIF('City Comparison'!$I$8:I12,'City Comparison'!I12)-1 -> 17 | F6: {=INDEX('City Comparison'!$A$8:$A$24,MATCH(ROWS($F$2:F6),$D$2:$D$18,0))} -> Poznań | G6: {=INDEX('City Comparison'!$H$8:$H$24,MATCH(ROWS($F$2:F6),$D$2:$D$18,0))} -> 1791 | H6: {=INDEX('City Comparison'!$I$8:$I$24,MATCH(ROWS($F$2:F6),$D$2:$D$18,0))} -> 2319
A7: 6 | D7: =RANK('City Comparison'!I13,'City Comparison'!$I$8:$I$24,0)+COUNTIF('City Comparison'!$I$8:I13,'City Comparison'!I13)-1 -> 7 | F7: {=INDEX('City Comparison'!$A$8:$A$24,MATCH(ROWS($F$2:F7),$D$2:$D$18,0))} -> Gdańsk | G7: {=INDEX('City Comparison'!$H$8:$H$24,MATCH(ROWS($F$2:F7),$D$2:$D$18,0))} -> 2194 | H7: {=INDEX('City Comparison'!$I$8:$I$24,MATCH(ROWS($F$2:F7),$D$2:$D$18,0))} -> 1618
A8: 7 | D8: =RANK('City Comparison'!I14,'City Comparison'!$I$8:$I$24,0)+COUNTIF('City Comparison'!$I$8:I14,'City Comparison'!I14)-1 -> 5 | F8: {=INDEX('City Comparison'!$A$8:$A$24,MATCH(ROWS($F$2:F8),$D$2:$D$18,0))} -> Rzeszów | G8: {=INDEX('City Comparison'!$H$8:$H$24,MATCH(ROWS($F$2:F8),$D$2:$D$18,0))} -> 1714 | H8: {=INDEX('City Comparison'!$I$8:$I$24,MATCH(ROWS($F$2:F8),$D$2:$D$18,0))} -> 1526
A9: 8 | D9: =RANK('City Comparison'!I15,'City Comparison'!$I$8:$I$24,0)+COUNTIF('City Comparison'!$I$8:I15,'City Comparison'!I15)-1 -> 8 | F9: {=INDEX('City Comparison'!$A$8:$A$24,MATCH(ROWS($F$2:F9),$D$2:$D$18,0))} -> Lublin | G9: {=INDEX('City Comparison'!$H$8:$H$24,MATCH(ROWS($F$2:F9),$D$2:$D$18,0))} -> 934 | H9: {=INDEX('City Comparison'!$I$8:$I$24,MATCH(ROWS($F$2:F9),$D$2:$D$18,0))} -> 1433
A10: 17 | D10: =RANK('City Comparison'!I16,'City Comparison'!$I$8:$I$24,0)+COUNTIF('City Comparison'!$I$8:I16,'City Comparison'!I16)-1 -> 15 | F10: {=INDEX('City Comparison'!$A$8:$A$24,MATCH(ROWS($F$2:F10),$D$2:$D$18,0))} -> Katowice | G10: {=INDEX('City Comparison'!$H$8:$H$24,MATCH(ROWS($F$2:F10),$D$2:$D$18,0))} -> 1269 | H10: {=INDEX('City Comparison'!$I$8:$I$24,MATCH(ROWS($F$2:F10),$D$2:$D$18,0))} -> 1420
A11: 9 | D11: =RANK('City Comparison'!I17,'City Comparison'!$I$8:$I$24,0)+COUNTIF('City Comparison'!$I$8:I17,'City Comparison'!I17)-1 -> 12 | F11: {=INDEX('City Comparison'!$A$8:$A$24,MATCH(ROWS($F$2:F11),$D$2:$D$18,0))} -> Bydgoszcz | G11: {=INDEX('City Comparison'!$H$8:$H$24,MATCH(ROWS($F$2:F11),$D$2:$D$18,0))} -> 345 | H11: {=INDEX('City Comparison'!$I$8:$I$24,MATCH(ROWS($F$2:F11),$D$2:$D$18,0))} -> 985
A12: 10 | D12: =RANK('City Comparison'!I18,'City Comparison'!$I$8:$I$24,0)+COUNTIF('City Comparison'!$I$8:I18,'City Comparison'!I18)-1 -> 14 | F12: {=INDEX('City Comparison'!$A$8:$A$24,MATCH(ROWS($F$2:F12),$D$2:$D$18,0))} -> Olsztyn | G12: {=INDEX('City Comparison'!$H$8:$H$24,MATCH(ROWS($F$2:F12),$D$2:$D$18,0))} -> 195 | H12: {=INDEX('City Comparison'!$I$8:$I$24,MATCH(ROWS($F$2:F12),$D$2:$D$18,0))} -> 778
A13: 11 | D13: =RANK('City Comparison'!I19,'City Comparison'!$I$8:$I$24,0)+COUNTIF('City Comparison'!$I$8:I19,'City Comparison'!I19)-1 -> 11 | F13: {=INDEX('City Comparison'!$A$8:$A$24,MATCH(ROWS($F$2:F13),$D$2:$D$18,0))} -> Szczecin | G13: {=INDEX('City Comparison'!$H$8:$H$24,MATCH(ROWS($F$2:F13),$D$2:$D$18,0))} -> 961 | H13: {=INDEX('City Comparison'!$I$8:$I$24,MATCH(ROWS($F$2:F13),$D$2:$D$18,0))} -> 680
... A18: 16 | D18: =RANK('City Comparison'!I24,'City Comparison'!$I$8:$I$24,0)+COUNTIF('City Comparison'!$I$8:I24,'City Comparison'!I24)-1 -> 4 | F18: {=INDEX('City Comparison'!$A$8:$A$24,MATCH(ROWS($F$2:F18),$D$2:$D$18,0))} -> Gdynia | G18: {=INDEX('City Comparison'!$H$8:$H$24,MATCH(ROWS($F$2:F18),$D$2:$D$18,0))} -> 296 | H18: {=INDEX('City Comparison'!$I$8:$I$24,MATCH(ROWS($F$2:F18),$D$2:$D$18,0))} -> 247
